Workbook

Sheet Summary
A1: Insurance Brokers Peer Model — Summary
A2: FY2025 snapshot, USD bn unless stated. Every figure links to the model sheets. Several inputs are still unverified — see Review_Flags before drawing conclusions.
A4: Company | B4: Revenue | C4: EBIT | D4: Net margin | E4: FCF margin | F4: Current ratio | G4: Interest coverage FY2025 (x) | H4: Severe-stress coverage (x) | I4: Severe-stress assessment | J4: EBIT basis
A5: =Peer_Comparison!A2 -> WTW | B5: =Peer_Comparison!B2 -> 9.708 | C5: =Peer_Comparison!C2 -> 2.234 | D5: =Peer_Comparison!E2 -> 0.16532756 | E5: =Peer_Comparison!J2 -> 0.1592501 | F5: =Peer_Comparison!F2 -> 1.2049414 | G5: =Financial_Ratios!D6 -> 8.5923077 | H5: =Peer_Comparison!N2 -> 6.4442308 | I5: =Stress_Test_Matrix!G4 -> Illustrative buffer | J5: =IF(ISNUMBER(SEARCH("proxy",Peer_Comparison!K2)),"Derived proxy","Reported") -> Reported
A6: =Peer_Comparison!A3 -> Aon | B6: =Peer_Comparison!B3 -> 17.181 | C6: =Peer_Comparison!C3 -> 4.344 | D6: =Peer_Comparison!E3 -> 0.21506315 | E6: =Peer_Comparison!J3 -> 0.16588091 | F6: =Peer_Comparison!F3 -> 0.95266272 | G6: =Financial_Ratios!D12 -> 5.3300613 | H6: =Peer_Comparison!N3 -> 3.997546 | I6: =Stress_Test_Matrix!G8 -> Pressure | J6: =IF(ISNUMBER(SEARCH("proxy",Peer_Comparison!K3)),"Derived proxy","Reported") -> Reported
A7: =Peer_Comparison!A4 -> MMC | B7: =Peer_Comparison!B4 -> 26.981 | C7: =Peer_Comparison!C4 -> 6.223 | D7: =Peer_Comparison!E4 -> 0.15418257 | E7: =Peer_Comparison!J4 -> 0.17049035 | F7: =Peer_Comparison!F4 -> 1.1904762 | G7: =Financial_Ratios!D18 -> 6.4822917 | H7: =Peer_Comparison!N4 -> 4.8617187 | I7: =Stress_Test_Matrix!G12 -> Pressure | J7: =IF(ISNUMBER(SEARCH("proxy",Peer_Comparison!K4)),"Derived proxy","Reported") -> Reported
A8: =Peer_Comparison!A5 -> AJG | B8: =Peer_Comparison!B5 -> 13.942 | C8: =Peer_Comparison!C5 -> 2.51 | D8: =Peer_Comparison!E5 -> 0.10715823 | E8: =Peer_Comparison!J5 -> 0.15062401 | F8: =Peer_Comparison!F5 -> 1.25 | G8: =Financial_Ratios!D24 -> 3.9280125 | H8: =Peer_Comparison!N5 -> 2.9460094 | I8: =Stress_Test_Matrix!G16 -> Pressure | J8: =IF(ISNUMBER(SEARCH("proxy",Peer_Comparison!K5)),"Derived proxy","Reported") -> Derived proxy
A9: =Peer_Comparison!A6 -> BRO | B9: =Peer_Comparison!B6 -> 5.902 | C9: =Peer_Comparison!C6 -> 1.668 | D9: =Peer_Comparison!E6 -> 0.17858353 | E9: =Peer_Comparison!J6 -> 0.21856998 | F9: =Peer_Comparison!F6 -> 1.4126984 | G9: =Financial_Ratios!D30 -> 5.6161616 | H9: =Peer_Comparison!N6 -> 4.2121212 | I9: =Stress_Test_Matrix!G20 -> Pressure | J9: =IF(ISNUMBER(SEARCH("proxy",Peer_Comparison!K6)),"Derived proxy","Reported") -> Derived proxy
A10: Peer median | B10: =MEDIAN(B5:B9) -> 13.942 | C10: =MEDIAN(C5:C9) -> 2.51 | D10: =MEDIAN(D5:D9) -> 0.16532756 | E10: =MEDIAN(E5:E9) -> 0.16588091 | F10: =MEDIAN(F5:F9) -> 1.2049414 | G10: =MEDIAN(G5:G9) -> 5.6161616 | H10: =MEDIAN(H5:H9) -> 4.2121212
A11: Median is across five companies and is descriptive only. AJG and BRO EBIT is a derived proxy, so EBIT-based figures are not strictly like-for-like.
A13: Data-quality scorecard — Financial_Metrics rows by status | H13: Verification progress — Source_Verification
A14: Company | B14: Needs review | C14: Partially verified | D14: Derived proxy | E14: Calculated | F14: Total rows | H14: Company | I14: Checked to primary | J14: Corrected | K14: Secondary discrepancies
A15: =A5 -> WTW | B15: =COUNTIFS(Financial_Metrics!$A$2:$A$71,$A15,Financial_Metrics!$J$2:$J$71,"Needs review*") -> 0 | C15: =COUNTIFS(Financial_Metrics!$A$2:$A$71,$A15,Financial_Metrics!$J$2:$J$71,"Partially verified*") -> 9 | D15: =COUNTIFS(Financial_Metrics!$A$2:$A$71,$A15,Financial_Metrics!$J$2:$J$71,"Derived proxy*") -> 0 | E15: =COUNTIFS(Financial_Metrics!$A$2:$A$71,$A15,Financial_Metrics!$J$2:$J$71,"Calculated*") -> 5 | F15: =SUM(B15:E15) -> 14 | H15: =A5 -> WTW | I15: =COUNTIFS(Source_Verification!$A$5:$A$51,$H15,Source_Verification!$K$5:$K$51,"Verified*")+COUNTIFS(Source_Verification!$A$5:$A$51,$H15,Source_Verification!$K$5:$K$51,"Corrected*") -> 24 | J15: =COUNTIFS(Source_Verification!$A$5:$A$51,$H15,Source_Verification!$K$5:$K$51,"Corrected*") -> 10 | K15: =COUNTIFS(Source_Verification!$A$5:$A$51,$H15,Source_Verification!$K$5:$K$51,"Discrepancy*") -> 19
A16: =A6 -> Aon | B16: =COUNTIFS(Financial_Metrics!$A$2:$A$71,$A16,Financial_Metrics!$J$2:$J$71,"Needs review*") -> 5 | C16: =COUNTIFS(Financial_Metrics!$A$2:$A$71,$A16,Financial_Metrics!$J$2:$J$71,"Partially verified*") -> 4 | D16: =COUNTIFS(Financial_Metrics!$A$2:$A$71,$A16,Financial_Metrics!$J$2:$J$71,"Derived proxy*") -> 0 | E16: =COUNTIFS(Financial_Metrics!$A$2:$A$71,$A16,Financial_Metrics!$J$2:$J$71,"Calculated*") -> 5 | F16: =SUM(B16:E16) -> 14 | H16: =A6 -> Aon | I16: =COUNTIFS(Source_Verification!$A$5:$A$51,$H16,Source_Verification!$K$5:$K$51,"Verified*")+COUNTIFS(Source_Verification!$A$5:$A$51,$H16,Source_Verification!$K$5:$K$51,"Corrected*") -> 0 | J16: =COUNTIFS(Source_Verification!$A$5:$A$51,$H16,Source_Verification!$K$5:$K$51,"Corrected*") -> 0 | K16: =COUNTIFS(Source_Verification!$A$5:$A$51,$H16,Source_Verification!$K$5:$K$51,"Discrepancy*") -> 0
A17: =A7 -> MMC | B17: =COUNTIFS(Financial_Metrics!$A$2:$A$71,$A17,Financial_Metrics!$J$2:$J$71,"Needs review*") -> 5 | C17: =COUNTIFS(Financial_Metrics!$A$2:$A$71,$A17,Financial_Metrics!$J$2:$J$71,"Partially verified*") -> 4 | D17: =COUNTIFS(Financial_Metrics!$A$2:$A$71,$A17,Financial_Metrics!$J$2:$J$71,"Derived proxy*") -> 0 | E17: =COUNTIFS(Financial_Metrics!$A$2:$A$71,$A17,Financial_Metrics!$J$2:$J$71,"Calculated*") -> 5 | F17: =SUM(B17:E17) -> 14 | H17: =A7 -> MMC | I17: =COUNTIFS(Source_Verification!$A$5:$A$51,$H17,Source_Verification!$K$5:$K$51,"Verified*")+COUNTIFS(Source_Verification!$A$5:$A$51,$H17,Source_Verification!$K$5:$K$51,"Corrected*") -> 0 | J17: =COUNTIFS(Source_Verification!$A$5:$A$51,$H17,Source_Verification!$K$5:$K$51,"Corrected*") -> 0 | K17: =COUNTIFS(Source_Verification!$A$5:$A$51,$H17,Source_Verification!$K$5:$K$51,"Discrepancy*") -> 0
A18: =A8 -> AJG | B18: =COUNTIFS(Financial_Metrics!$A$2:$A$71,$A18,Financial_Metrics!$J$2:$J$71,"Needs review*") -> 5 | C18: =COUNTIFS(Financial_Metrics!$A$2:$A$71,$A18,Financial_Metrics!$J$2:$J$71,"Partially verified*") -> 3 | D18: =COUNTIFS(Financial_Metrics!$A$2:$A$71,$A18,Financial_Metrics!$J$2:$J$71,"Derived proxy*") -> 1 | E18: =COUNTIFS(Financial_Metrics!$A$2:$A$71,$A18,Financial_Metrics!$J$2:$J$71,"Calculated*") -> 5 | F18: =SUM(B18:E18) -> 14 | H18: =A8 -> AJG | I18: =COUNTIFS(Source_Verification!$A$5:$A$51,$H18,Source_Verification!$K$5:$K$51,"Verified*")+COUNTIFS(Source_Verification!$A$5:$A$51,$H18,Source_Verification!$K$5:$K$51,"Corrected*") -> 0 | J18: =COUNTIFS(Source_Verification!$A$5:$A$51,$H18,Source_Verification!$K$5:$K$51,"Corrected*") -> 0 | K18: =COUNTIFS(Source_Verification!$A$5:$A$51,$H18,Source_Verification!$K$5:$K$51,"Discrepancy*") -> 0
A19: =A9 -> BRO | B19: =COUNTIFS(Financial_Metrics!$A$2:$A$71,$A19,Financial_Metrics!$J$2:$J$71,"Needs review*") -> 5 | C19: =COUNTIFS(Financial_Metrics!$A$2:$A$71,$A19,Financial_Metrics!$J$2:$J$71,"Partially verified*") -> 3 | D19: =COUNTIFS(Financial_Metrics!$A$2:$A$71,$A19,Financial_Metrics!$J$2:$J$71,"Derived proxy*") -> 1 | E19: =COUNTIFS(Financial_Metrics!$A$2:$A$71,$A19,Financial_Metrics!$J$2:$J$71,"Calculated*") -> 5 | F19: =SUM(B19:E19) -> 14 | H19: =A9 -> BRO | I19: =COUNTIFS(Source_Verification!$A$5:$A$51,$H19,Source_Verification!$K$5:$K$51,"Verified*")+COUNTIFS(Source_Verification!$A$5:$A$51,$H19,Source_Verification!$K$5:$K$51,"Corrected*") -> 0 | J19: =COUNTIFS(Source_Verification!$A$5:$A$51,$H19,Source_Verification!$K$5:$K$51,"Corrected*") -> 0 | K19: =COUNTIFS(Source_Verification!$A$5:$A$51,$H19,Source_Verification!$K$5:$K$51,"Discrepancy*") -> 0
A20: Total | B20: =SUM(B15:B19) -> 20 | C20: =SUM(C15:C19) -> 23 | D20: =SUM(D15:D19) -> 2 | E20: =SUM(E15:E19) -> 25 | F20: =SUM(F15:F19) -> 70 | H20: Total | I20: =SUM(I15:I19) -> 24 | J20: =SUM(J15:J19) -> 10 | K20: =SUM(K15:K19) -> 19
A21: Input rows still marked “Needs review” | B21: =IFERROR(B20/SUM(B20:D20),"") -> 0.44444444 | C21: Excludes Calculated rows, which depend on those inputs. | H21: Only WTW has been checked so far; the other four show 0 until verified.
A23: Review flags
A24: Flags logged | B24: =COUNTA(Review_Flags!$A$2:$A$20) -> 19
A25: Open | B25: =COUNTIF(Review_Flags!$F$2:$F$20,"Open") -> 11
A26: High priority and open | B26: =COUNTIFS(Review_Flags!$A$2:$A$20,"High",Review_Flags!$F$2:$F$20,"Open") -> 8

Sheet Financial_Metrics
A1: Company | B1: Metric (USD bn unless ratio / %) | C1: 2021 | D1: 2022 | E1: 2023 | F1: 2024 | G1: 2025 | H1: 2026_TTM | I1: Source URL | J1: Data Status | K1: Review Notes | M1: Legend
A2: WTW | B2: Total Revenue | C2: 9 | D2: 8.87 | E2: 9.483 | F2: 9.93 | G2: 9.708 | H2: 10.1 | I2: https://www.sec.gov/Archives/edgar/data/1140536/000119312526069307/wtw-20251231.htm | J2: Partially verified — FY2023–FY2025 | K2: FY2023–FY2025 values reconciled to cited FY2025 Form 10-K. 2021–2022 and 2026_TTM are not verified in this pass; see Audit_Log. | M2: Blue = hardcoded input
A3: WTW | B3: Revenue Growth YoY | C3: n/a | D3: =IFERROR(D2/C2-1,"") -> -0.014444444 | E3: =IFERROR(E2/D2-1,"") -> 0.069109357 | F3: =IFERROR(F2/E2-1,"") -> 0.047136982 | G3: =IFERROR(G2/F2-1,"") -> -0.022356495 | H3: n/a — TTM comparator unavailable | I3: Calculated | J3: Calculated (FY only) | K3: FY2024 and FY2025 growth use the reconciled FY2023–FY2025 revenue series. FY2023 growth still depends on the unverified FY2022 input. 2026_TTM growth is intentionally n/a because no prior comparable TTM period is provided. | M3: Black = formula
A4: WTW | B4: Operating Income (EBIT) | C4: 1.75 | D4: 1.81 | E4: 1.365 | F4: 0.627 | G4: 2.234 | H4: 1.77 | I4: https://www.sec.gov/Archives/edgar/data/1140536/000119312526069307/wtw-20251231.htm | J4: Partially verified — FY2023–FY2025 | K4: FY2023–FY2025 values reconciled to cited FY2025 Form 10-K. 2021–2022 and 2026_TTM are not verified in this pass; see Audit_Log.
A5: WTW | B5: Net Income | C5: 4.22 | D5: 1.01 | E5: 1.055 | F5: -0.098 | G5: 1.605 | H5: 1.56 | I5: https://www.sec.gov/Archives/edgar/data/1140536/000119312526069307/wtw-20251231.htm | J5: Partially verified — FY2023–FY2025 | K5: FY2023–FY2025 reconciled to WTW FY2025 Form 10-K, net income attributable to WTW (checked 2026-10-28). FY2023 was 1.064 (consolidated net income) and is now 1.055 (attributable). 2021–2022 match secondary sources after rounding; 2026_TTM not verified. | M5: Status colours (column J)
A6: WTW | B6: Net Profit Margin | C6: =IFERROR(C5/C2,"") -> 0.46888889 | D6: =IFERROR(D5/D2,"") -> 0.11386697 | E6: =IFERROR(E5/E2,"") -> 0.11125171 | F6: =IFERROR(F5/F2,"") -> -0.0098690836 | G6: =IFERROR(G5/G2,"") -> 0.16532756 | H6: =IFERROR(H5/H2,"") -> 0.15445545 | I6: Calculated | J6: Calculated — inputs require review | K6: Formula is live; output reliability depends on source inputs. See Audit_Log for source status. | M6: Needs review
A7: WTW | B7: Operating Cash Flow | C7: 2.11 | D7: 0.97 | E7: 1.345 | F7: 1.512 | G7: 1.775 | H7: 2.04 | I7: https://www.sec.gov/Archives/edgar/data/1140536/000119312526069307/wtw-20251231.htm | J7: Partially verified — FY2023–FY2025 | K7: FY2023–FY2025 reconciled to WTW FY2025 Form 10-K cash-flow statement (checked 2026-10-28). 2021–2022 differ from secondary sources (2.061 / 0.812) and are not changed until checked to primary filings. 2026_TTM period end is undefined; see Source_Verification. | M7: Partially verified
A8: WTW | B8: Capital Expenditures | C8: 0.28 | D8: 0.3 | E8: 0.242 | F8: 0.245 | G8: 0.229 | H8: 0.35 | I8: https://www.sec.gov/Archives/edgar/data/1140536/000119312526069307/wtw-20251231.htm | J8: Partially verified — FY2023–FY2025 | K8: FY2023–FY2025 reconciled to the cash-flow line 'Additions to fixed assets and software' (checked 2026-10-28). 2021–2022 differ from secondary sources (0.201 / 0.204) and are not changed yet. | M8: Derived proxy
A9: WTW | B9: Free Cash Flow | C9: =IFERROR(C7-C8,"") -> 1.83 | D9: =IFERROR(D7-D8,"") -> 0.67 | E9: =IFERROR(E7-E8,"") -> 1.103 | F9: =IFERROR(F7-F8,"") -> 1.267 | G9: =IFERROR(G7-G8,"") -> 1.546 | H9: =IFERROR(H7-H8,"") -> 1.69 | I9: Calculated | J9: Calculated — inputs require review | K9: Formula is live; output reliability depends on source inputs. See Audit_Log for source status. | M9: Calculated
A10: WTW | B10: Current Assets | C10: 13.5 | D10: 13.83 | E10: 14.06 | F10: 15.105 | G10: 16.874 | H10: 16.75 | I10: https://www.sec.gov/Archives/edgar/data/1140536/000119312526069307/wtw-20251231.htm | J10: Partially verified — FY2024–FY2025 | K10: FY2024–FY2025 reconciled to the FY2025 Form 10-K balance sheet (includes fiduciary assets). FY2021–FY2023 differ from secondary sources (13.433 / 15.835 / 18.488 mn basis) and need the older 10-Ks.
A11: WTW | B11: Current Liabilities | C11: 12.6 | D11: 12.93 | E11: 13.26 | F11: 12.598 | G11: 14.004 | H11: 15.25 | I11: https://www.sec.gov/Archives/edgar/data/1140536/000119312526069307/wtw-20251231.htm | J11: Partially verified — FY2024–FY2025 | K11: FY2024–FY2025 reconciled to the FY2025 Form 10-K balance sheet (includes fiduciary liabilities). FY2021–FY2023 differ from secondary sources and need the older 10-Ks.
A12: WTW | B12: Current Ratio | C12: =IFERROR(C10/C11,"") -> 1.0714286 | D12: =IFERROR(D10/D11,"") -> 1.0696056 | E12: =IFERROR(E10/E11,"") -> 1.0603318 | F12: =IFERROR(F10/F11,"") -> 1.1989998 | G12: =IFERROR(G10/G11,"") -> 1.2049414 | H12: =IFERROR(H10/H11,"") -> 1.0983607 | I12: Calculated | J12: Calculated — inputs require review | K12: Formula is live; output reliability depends on source inputs. See Audit_Log for source status.
A13: WTW | B13: Total Debt | C13: 5.49 | D13: 5.48 | E13: 5.95 | F13: 5.929 | G13: 6.903 | H13: 7.1 | I13: https://www.sec.gov/Archives/edgar/data/1140536/000119312526069307/wtw-20251231.htm | J13: Partially verified — FY2024–FY2025 | K13: FY2024–FY2025 = current debt + long-term debt + lease liabilities, per the FY2025 10-K balance sheet (excluding leases: 5.309 / 6.306). FY2021–FY2023 are not reconciled. Definition choice is open: see Review_Flags.
A14: WTW | B14: Interest Expense | C14: 0.28 | D14: 0.3 | E14: 0.235 | F14: 0.263 | G14: 0.26 | H14: 0.34 | I14: https://www.sec.gov/Archives/edgar/data/1140536/000119312526069307/wtw-20251231.htm | J14: Partially verified — FY2023–FY2025 | K14: FY2023–FY2025 reconciled to the FY2025 Form 10-K income statement (checked 2026-10-28). FY2023 was 0.30 in the previous version; the filing shows 0.235. 2021–2022 differ from secondary sources (0.211 / 0.208).
A15: WTW | B15: Interest Coverage Ratio | C15: =IFERROR(C4/C14,"") -> 6.25 | D15: =IFERROR(D4/D14,"") -> 6.0333333 | E15: =IFERROR(E4/E14,"") -> 5.8085106 | F15: =IFERROR(F4/F14,"") -> 2.3840304 | G15: =IFERROR(G4/G14,"") -> 8.5923077 | H15: =IFERROR(H4/H14,"") -> 5.2058824 | I15: Calculated | J15: Calculated — inputs require review | K15: Formula is live; output reliability depends on source inputs. See Audit_Log for source status.
A16: Aon | B16: Total Revenue | C16: 12.2 | D16: 12.5 | E16: 13.376 | F16: 15.698 | G16: 17.181 | H16: 17.58 | I16: https://www.sec.gov/Archives/edgar/data/315293/000162828026008116/aon-20251231.htm | J16: Partially verified — FY2023–FY2025 | K16: FY2023–FY2025 values reconciled to cited FY2025 Form 10-K. 2021–2022 and 2026_TTM are not verified in this pass; see Audit_Log.
A17: Aon | B17: Revenue Growth YoY | C17: n/a | D17: =IFERROR(D16/C16-1,"") -> 0.024590164 | E17: =IFERROR(E16/D16-1,"") -> 0.07008 | F17: =IFERROR(F16/E16-1,"") -> 0.1735945 | G17: =IFERROR(G16/F16-1,"") -> 0.094470633 | H17: n/a — TTM comparator unavailable | I17: Calculated | J17: Calculated (FY only) | K17: FY2024 and FY2025 growth use the reconciled FY2023–FY2025 revenue series. FY2023 growth still depends on the unverified FY2022 input. 2026_TTM growth is intentionally n/a because no prior comparable TTM period is provided.
A18: Aon | B18: Operating Income (EBIT) | C18: 3.1 | D18: 3.2 | E18: 3.785 | F18: 3.835 | G18: 4.344 | H18: 4.2 | I18: https://www.sec.gov/Archives/edgar/data/315293/000162828026008116/aon-20251231.htm | J18: Partially verified — FY2023–FY2025 | K18: FY2023–FY2025 values reconciled to cited FY2025 Form 10-K. 2021–2022 and 2026_TTM are not verified in this pass; see Audit_Log.
A19: Aon | B19: Net Income | C19: 2.4 | D19: 2.6 | E19: 2.564 | F19: 2.654 | G19: 3.695 | H19: 3.91 | I19: https://www.sec.gov/Archives/edgar/data/315293/000162828026008116/aon-20251231.htm | J19: Partially verified — FY2023–FY2025 | K19: FY2023–FY2025 values reconciled to cited FY2025 Form 10-K. 2021–2022 and 2026_TTM are not verified in this pass; see Audit_Log.
A20: Aon | B20: Net Profit Margin | C20: =IFERROR(C19/C16,"") -> 0.19672131 | D20: =IFERROR(D19/D16,"") -> 0.208 | E20: =IFERROR(E19/E16,"") -> 0.1916866 | F20: =IFERROR(F19/F16,"") -> 0.16906612 | G20: =IFERROR(G19/G16,"") -> 0.21506315 | H20: =IFERROR(H19/H16,"") -> 0.22241183 | I20: Calculated | J20: Calculated — inputs require review | K20: Formula is live; output reliability depends on source inputs. See Audit_Log for source status.
A21: Aon | B21: Operating Cash Flow | C21: 2.6 | D21: 2.8 | E21: 3.1 | F21: 3.2 | G21: 3.5 | H21: 3.8 | I21: https://www.sec.gov/Archives/edgar/data/315293/000162828026008116/aon-20251231.htm | J21: Needs review | K21: Historical and TTM values have not all been reconciled to the cash-flow statement; do not treat as confirmed.
A22: Aon | B22: Capital Expenditures | C22: 0.4 | D22: 0.45 | E22: 0.5 | F22: 0.55 | G22: 0.65 | H22: 0.73 | I22: https://www.sec.gov/Archives/edgar/data/315293/000162828026008116/aon-20251231.htm | J22: Needs review | K22: Historical and TTM values have not all been reconciled to the cash-flow statement; do not treat as confirmed.
A23: Aon | B23: Free Cash Flow | C23: =IFERROR(C21-C22,"") -> 2.2 | D23: =IFERROR(D21-D22,"") -> 2.35 | E23: =IFERROR(E21-E22,"") -> 2.6 | F23: =IFERROR(F21-F22,"") -> 2.65 | G23: =IFERROR(G21-G22,"") -> 2.85 | H23: =IFERROR(H21-H22,"") -> 3.07 | I23: Calculated | J23: Calculated — inputs require review | K23: Formula is live; output reliability depends on source inputs. See Audit_Log for source status.
A24: Aon | B24: Current Assets | C24: 14.1 | D24: 14.5 | E24: 15.1 | F24: 15.8 | G24: 16.1 | H24: 16.5 | I24: https://www.sec.gov/Archives/edgar/data/315293/000162828026008116/aon-20251231.htm | J24: Needs review | K24: Not independently reconciled to the corresponding balance-sheet line items in this pass. Ratios using this row are provisional.
A25: Aon | B25: Current Liabilities | C25: 15.2 | D25: 15.5 | E25: 16.2 | F25: 16.5 | G25: 16.9 | H25: 17.1 | I25: https://www.sec.gov/Archives/edgar/data/315293/000162828026008116/aon-20251231.htm | J25: Needs review | K25: Not independently reconciled to the corresponding balance-sheet line items in this pass. Ratios using this row are provisional.
A26: Aon | B26: Current Ratio | C26: =IFERROR(C24/C25,"") -> 0.92763158 | D26: =IFERROR(D24/D25,"") -> 0.93548387 | E26: =IFERROR(E24/E25,"") -> 0.93209877 | F26: =IFERROR(F24/F25,"") -> 0.95757576 | G26: =IFERROR(G24/G25,"") -> 0.95266272 | H26: =IFERROR(H24/H25,"") -> 0.96491228 | I26: Calculated | J26: Calculated — inputs require review | K26: Formula is live; output reliability depends on source inputs. See Audit_Log for source status.
A27: Aon | B27: Total Debt | C27: 11.2 | D27: 11.5 | E27: 11.8 | F27: 12.1 | G27: 14.5 | H27: 15.87 | I27: https://www.sec.gov/Archives/edgar/data/315293/000162828026008116/aon-20251231.htm | J27: Needs review | K27: Not independently reconciled to the corresponding balance-sheet line items in this pass. Ratios using this row are provisional.
A28: Aon | B28: Interest Expense | C28: 0.42 | D28: 0.45 | E28: 0.48 | F28: 0.788 | G28: 0.815 | H28: 0.52 | I28: https://www.sec.gov/Archives/edgar/data/315293/000162828026008116/aon-20251231.htm | J28: Partially verified | K28: FY2023–FY2025 verified only where updated; any blank/unchanged year, 2021–2022, and 2026_TTM require source-line review. Definitions can differ across issuers.
A29: Aon | B29: Interest Coverage Ratio | C29: =IFERROR(C18/C28,"") -> 7.3809524 | D29: =IFERROR(D18/D28,"") -> 7.1111111 | E29: =IFERROR(E18/E28,"") -> 7.8854167 | F29: =IFERROR(F18/F28,"") -> 4.8667513 | G29: =IFERROR(G18/G28,"") -> 5.3300613 | H29: =IFERROR(H18/H28,"") -> 8.0769231 | I29: Calculated | J29: Calculated — inputs require review | K29: Formula is live; output reliability depends on source inputs. See Audit_Log for source status.
A30: MMC | B30: Total Revenue | C30: 19.82 | D30: 20.7 | E30: 22.736 | F30: 24.458 | G30: 26.981 | H30: 27.95 | I30: https://www.sec.gov/Archives/edgar/data/62709/000006270926000022/mrsh-20251231.htm | J30: Partially verified — FY2023–FY2025 | K30: FY2023–FY2025 values reconciled to cited FY2025 Form 10-K. 2021–2022 and 2026_TTM are not verified in this pass; see Audit_Log.
A31: MMC | B31: Revenue Growth YoY | C31: n/a | D31: =IFERROR(D30/C30-1,"") -> 0.044399596 | E31: =IFERROR(E30/D30-1,"") -> 0.098357488 | F31: =IFERROR(F30/E30-1,"") -> 0.075738916 | G31: =IFERROR(G30/F30-1,"") -> 0.10315643 | H31: n/a — TTM comparator unavailable | I31: Calculated | J31: Calculated (FY only) | K31: FY2024 and FY2025 growth use the reconciled FY2023–FY2025 revenue series. FY2023 growth still depends on the unverified FY2022 input. 2026_TTM growth is intentionally n/a because no prior comparable TTM period is provided.
A32: MMC | B32: Operating Income (EBIT) | C32: 4.3 | D32: 4.6 | E32: 5.282 | F32: 5.817 | G32: 6.223 | H32: 6.4 | I32: https://www.sec.gov/Archives/edgar/data/62709/000006270926000022/mrsh-20251231.htm | J32: Partially verified — FY2023–FY2025 | K32: FY2023–FY2025 values reconciled to cited FY2025 Form 10-K. 2021–2022 and 2026_TTM are not verified in this pass; see Audit_Log.
A33: MMC | B33: Net Income | C33: 3.1 | D33: 3.4 | E33: 3.756 | F33: 4.06 | G33: 4.16 | H33: 4.8 | I33: https://www.sec.gov/Archives/edgar/data/62709/000006270926000022/mrsh-20251231.htm | J33: Partially verified — FY2023–FY2025 | K33: FY2023–FY2025 values reconciled to cited FY2025 Form 10-K. 2021–2022 and 2026_TTM are not verified in this pass; see Audit_Log.
A34: MMC | B34: Net Profit Margin | C34: =IFERROR(C33/C30,"") -> 0.15640767 | D34: =IFERROR(D33/D30,"") -> 0.16425121 | E34: =IFERROR(E33/E30,"") -> 0.16520056 | F34: =IFERROR(F33/F30,"") -> 0.16599886 | G34: =IFERROR(G33/G30,"") -> 0.15418257 | H34: =IFERROR(H33/H30,"") -> 0.17173524 | I34: Calculated | J34: Calculated — inputs require review | K34: Formula is live; output reliability depends on source inputs. See Audit_Log for source status.
A35: MMC | B35: Operating Cash Flow | C35: 3.9 | D35: 4.2 | E35: 4.6 | F35: 4.9 | G35: 5.3 | H35: 5.8 | I35: https://www.sec.gov/Archives/edgar/data/62709/000006270926000022/mrsh-20251231.htm | J35: Needs review | K35: Historical and TTM values have not all been reconciled to the cash-flow statement; do not treat as confirmed.
A36: MMC | B36: Capital Expenditures | C36: 0.5 | D36: 0.55 | E36: 0.6 | F36: 0.65 | G36: 0.7 | H36: 0.78 | I36: https://www.sec.gov/Archives/edgar/data/62709/000006270926000022/mrsh-20251231.htm | J36: Needs review | K36: Historical and TTM values have not all been reconciled to the cash-flow statement; do not treat as confirmed.
A37: MMC | B37: Free Cash Flow | C37: =IFERROR(C35-C36,"") -> 3.4 | D37: =IFERROR(D35-D36,"") -> 3.65 | E37: =IFERROR(E35-E36,"") -> 4 | F37: =IFERROR(F35-F36,"") -> 4.25 | G37: =IFERROR(G35-G36,"") -> 4.6 | H37: =IFERROR(H35-H36,"") -> 5.02 | I37: Calculated | J37: Calculated — inputs require review | K37: Formula is live; output reliability depends on source inputs. See Audit_Log for source status.
A38: MMC | B38: Current Assets | C38: 22.1 | D38: 23.4 | E38: 24.8 | F38: 26.1 | G38: 27.5 | H38: 28.9 | I38: https://www.sec.gov/Archives/edgar/data/62709/000006270926000022/mrsh-20251231.htm | J38: Needs review | K38: Not independently reconciled to the corresponding balance-sheet line items in this pass. Ratios using this row are provisional.
A39: MMC | B39: Current Liabilities | C39: 19.5 | D39: 20.1 | E39: 21.3 | F39: 22.4 | G39: 23.1 | H39: 24.2 | I39: https://www.sec.gov/Archives/edgar/data/62709/000006270926000022/mrsh-20251231.htm | J39: Needs review | K39: Not independently reconciled to the corresponding balance-sheet line items in this pass. Ratios using this row are provisional.
A40: MMC | B40: Current Ratio | C40: =IFERROR(C38/C39,"") -> 1.1333333 | D40: =IFERROR(D38/D39,"") -> 1.1641791 | E40: =IFERROR(E38/E39,"") -> 1.1643192 | F40: =IFERROR(F38/F39,"") -> 1.1651786 | G40: =IFERROR(G38/G39,"") -> 1.1904762 | H40: =IFERROR(H38/H39,"") -> 1.1942149 | I40: Calculated | J40: Calculated — inputs require review | K40: Formula is live; output reliability depends on source inputs. See Audit_Log for source status.
A41: MMC | B41: Total Debt | C41: 11.4 | D41: 11.9 | E41: 12.3 | F41: 12.8 | G41: 13.4 | H41: 14.1 | I41: https://www.sec.gov/Archives/edgar/data/62709/000006270926000022/mrsh-20251231.htm | J41: Needs review | K41: Not independently reconciled to the corresponding balance-sheet line items in this pass. Ratios using this row are provisional.
A42: MMC | B42: Interest Expense | C42: 0.5 | D42: 0.52 | E42: 0.578 | F42: 0.7 | G42: 0.96 | H42: 0.62 | I42: https://www.sec.gov/Archives/edgar/data/62709/000006270926000022/mrsh-20251231.htm | J42: Partially verified | K42: FY2023–FY2025 verified only where updated; any blank/unchanged year, 2021–2022, and 2026_TTM require source-line review. Definitions can differ across issuers.
A43: MMC | B43: Interest Coverage Ratio | C43: =IFERROR(C32/C42,"") -> 8.6 | D43: =IFERROR(D32/D42,"") -> 8.8461538 | E43: =IFERROR(E32/E42,"") -> 9.1384083 | F43: =IFERROR(F32/F42,"") -> 8.31 | G43: =IFERROR(G32/G42,"") -> 6.4822917 | H43: =IFERROR(H32/H42,"") -> 10.322581 | I43: Calculated | J43: Calculated — inputs require review | K43: Formula is live; output reliability depends on source inputs. See Audit_Log for source status.
A44: AJG | B44: Total Revenue | C44: 7.97 | D44: 8.4 | E44: 10.072 | F44: 11.555 | G44: 13.942 | H44: 15.75 | I44: https://www.sec.gov/Archives/edgar/data/354190/000162828026008662/ajg-20251231.htm | J44: Partially verified — FY2023–FY2025 | K44: FY2023–FY2025 values reconciled to cited FY2025 Form 10-K. 2021–2022 and 2026_TTM are not verified in this pass; see Audit_Log.
A45: AJG | B45: Revenue Growth YoY | C45: n/a | D45: =IFERROR(D44/C44-1,"") -> 0.053952321 | E45: =IFERROR(E44/D44-1,"") -> 0.19904762 | F45: =IFERROR(F44/E44-1,"") -> 0.14723987 | G45: =IFERROR(G44/F44-1,"") -> 0.20657724 | H45: n/a — TTM comparator unavailable | I45: Calculated | J45: Calculated (FY only) | K45: FY2024 and FY2025 growth use the reconciled FY2023–FY2025 revenue series. FY2023 growth still depends on the unverified FY2022 input. 2026_TTM growth is intentionally n/a because no prior comparable TTM period is provided.
A46: AJG | B46: Operating Income / EBIT Proxy (see notes) | C46: 1.4 | D46: 1.55 | E46: 1.482 | F46: 2.256 | G46: 2.51 | H46: 3.1 | I46: https://www.sec.gov/Archives/edgar/data/354190/000162828026008662/ajg-20251231.htm | J46: Derived proxy — FY2023–FY2025 | K46: FY2023–FY2025 values are income before income taxes plus interest expense; not reported EBIT and not fully comparable with other companies. 2021–2022 and 2026_TTM require review.
A47: AJG | B47: Net Income | C47: 0.9 | D47: 1.05 | E47: 0.97 | F47: 1.463 | G47: 1.494 | H47: 2.2 | I47: https://www.sec.gov/Archives/edgar/data/354190/000162828026008662/ajg-20251231.htm | J47: Partially verified — FY2023–FY2025 | K47: FY2023–FY2025 values reconciled to cited FY2025 Form 10-K. 2021–2022 and 2026_TTM are not verified in this pass; see Audit_Log.
A48: AJG | B48: Net Profit Margin | C48: =IFERROR(C47/C44,"") -> 0.11292346 | D48: =IFERROR(D47/D44,"") -> 0.125 | E48: =IFERROR(E47/E44,"") -> 0.096306593 | F48: =IFERROR(F47/F44,"") -> 0.12661186 | G48: =IFERROR(G47/G44,"") -> 0.10715823 | H48: =IFERROR(H47/H44,"") -> 0.13968254 | I48: Calculated | J48: Calculated — inputs require review | K48: Formula is live; output reliability depends on source inputs. See Audit_Log for source status.
A49: AJG | B49: Operating Cash Flow | C49: 1.25 | D49: 1.4 | E49: 1.7 | F49: 1.7 | G49: 2.4 | H49: 2.85 | I49: https://www.sec.gov/Archives/edgar/data/354190/000162828026006662/ajg-20251231.htm | J49: Needs review | K49: Historical and TTM values have not all been reconciled to the cash-flow statement; do not treat as confirmed.
A50: AJG | B50: Capital Expenditures | C50: 0.15 | D50: 0.18 | E50: 0.22 | F50: 0.22 | G50: 0.3 | H50: 0.35 | I50: https://www.sec.gov/Archives/edgar/data/354190/000162828026006662/ajg-20251231.htm | J50: Needs review | K50: Historical and TTM values have not all been reconciled to the cash-flow statement; do not treat as confirmed.
A51: AJG | B51: Free Cash Flow | C51: =IFERROR(C49-C50,"") -> 1.1 | D51: =IFERROR(D49-D50,"") -> 1.22 | E51: =IFERROR(E49-E50,"") -> 1.48 | F51: =IFERROR(F49-F50,"") -> 1.48 | G51: =IFERROR(G49-G50,"") -> 2.1 | H51: =IFERROR(H49-H50,"") -> 2.5 | I51: Calculated | J51: Calculated — inputs require review | K51: Formula is live; output reliability depends on source inputs. See Audit_Log for source status.
A52: AJG | B52: Current Assets | C52: 10.2 | D52: 11.4 | E52: 12.8 | F52: 14.1 | G52: 16.5 | H52: 18.2 | I52: https://www.sec.gov/Archives/edgar/data/354190/000162828026006662/ajg-20251231.htm | J52: Needs review | K52: Not independently reconciled to the corresponding balance-sheet line items in this pass. Ratios using this row are provisional.
A53: AJG | B53: Current Liabilities | C53: 8.5 | D53: 9.2 | E53: 10.4 | F53: 11.5 | G53: 13.2 | H53: 14.6 | I53: https://www.sec.gov/Archives/edgar/data/354190/000162828026006662/ajg-20251231.htm | J53: Needs review | K53: Not independently reconciled to the corresponding balance-sheet line items in this pass. Ratios using this row are provisional.
A54: AJG | B54: Current Ratio | C54: =IFERROR(C52/C53,"") -> 1.2 | D54: =IFERROR(D52/D53,"") -> 1.2391304 | E54: =IFERROR(E52/E53,"") -> 1.2307692 | F54: =IFERROR(F52/F53,"") -> 1.226087 | G54: =IFERROR(G52/G53,"") -> 1.25 | H54: =IFERROR(H52/H53,"") -> 1.2465753 | I54: Calculated | J54: Calculated — inputs require review | K54: Formula is live; output reliability depends on source inputs. See Audit_Log for source status.
A55: AJG | B55: Total Debt | C55: 5.1 | D55: 5.4 | E55: 6.2 | F55: 6.8 | G55: 7.9 | H55: 8.7 | I55: https://www.sec.gov/Archives/edgar/data/354190/000162828026006662/ajg-20251231.htm | J55: Needs review | K55: Not independently reconciled to the corresponding balance-sheet line items in this pass. Ratios using this row are provisional.
A56: AJG | B56: Interest Expense | C56: 0.2 | D56: 0.22 | E56: 0.25 | F56: 0.381 | G56: 0.639 | H56: 0.36 | I56: https://www.sec.gov/Archives/edgar/data/354190/000162828026008662/ajg-20251231.htm | J56: Partially verified | K56: FY2023–FY2025 verified only where updated; any blank/unchanged year, 2021–2022, and 2026_TTM require source-line review. Definitions can differ across issuers.
A57: AJG | B57: Interest Coverage Ratio | C57: =IFERROR(C46/C56,"") -> 7 | D57: =IFERROR(D46/D56,"") -> 7.0454545 | E57: =IFERROR(E46/E56,"") -> 5.928 | F57: =IFERROR(F46/F56,"") -> 5.9212598 | G57: =IFERROR(G46/G56,"") -> 3.9280125 | H57: =IFERROR(H46/H56,"") -> 8.6111111 | I57: Calculated | J57: Calculated — inputs require review | K57: Formula is live; output reliability depends on source inputs. See Audit_Log for source status.
A58: BRO | B58: Total Revenue | C58: 3.05 | D58: 3.5 | E58: 4.257 | F58: 4.805 | G58: 5.902 | H58: 6.66 | I58: https://www.sec.gov/Archives/edgar/data/79282/000119312526046984/bro-20251231.htm | J58: Partially verified — FY2023–FY2025 | K58: FY2023–FY2025 values reconciled to cited FY2025 Form 10-K. 2021–2022 and 2026_TTM are not verified in this pass; see Audit_Log.
A59: BRO | B59: Revenue Growth YoY | C59: n/a | D59: =IFERROR(D58/C58-1,"") -> 0.14754098 | E59: =IFERROR(E58/D58-1,"") -> 0.21628571 | F59: =IFERROR(F58/E58-1,"") -> 0.12872915 | G59: =IFERROR(G58/F58-1,"") -> 0.22830385 | H59: n/a — TTM comparator unavailable | I59: Calculated | J59: Calculated (FY only) | K59: FY2024 and FY2025 growth use the reconciled FY2023–FY2025 revenue series. FY2023 growth still depends on the unverified FY2022 input. 2026_TTM growth is intentionally n/a because no prior comparable TTM period is provided.
A60: BRO | B60: Operating Income / EBIT Proxy (see notes) | C60: 0.75 | D60: 0.9 | E60: 1.336 | F60: 1.496 | G60: 1.668 | H60: 1.85 | I60: https://www.sec.gov/Archives/edgar/data/79282/000119312526046984/bro-20251231.htm | J60: Derived proxy — FY2023–FY2025 | K60: FY2023–FY2025 values are income before income taxes plus interest expense; not reported EBIT and not fully comparable with other companies. 2021–2022 and 2026_TTM require review.
A61: BRO | B61: Net Income | C61: 0.55 | D61: 0.65 | E61: 0.871 | F61: 0.993 | G61: 1.054 | H61: 1.3 | I61: https://www.sec.gov/Archives/edgar/data/79282/000119312526046984/bro-20251231.htm | J61: Partially verified — FY2023–FY2025 | K61: FY2023–FY2025 values reconciled to cited FY2025 Form 10-K. 2021–2022 and 2026_TTM are not verified in this pass; see Audit_Log.
A62: BRO | B62: Net Profit Margin | C62: =IFERROR(C61/C58,"") -> 0.18032787 | D62: =IFERROR(D61/D58,"") -> 0.18571429 | E62: =IFERROR(E61/E58,"") -> 0.20460418 | F62: =IFERROR(F61/F58,"") -> 0.20665973 | G62: =IFERROR(G61/G58,"") -> 0.17858353 | H62: =IFERROR(H61/H58,"") -> 0.1951952 | I62: Calculated | J62: Calculated — inputs require review | K62: Formula is live; output reliability depends on source inputs. See Audit_Log for source status.
A63: BRO | B63: Operating Cash Flow | C63: 0.7 | D63: 0.82 | E63: 0.95 | F63: 1.05 | G63: 1.4 | H63: 1.65 | I63: https://www.sec.gov/Archives/edgar/data/79282/000119312526046984/bro-20251231.htm | J63: Needs review | K63: Historical and TTM values have not all been reconciled to the cash-flow statement; do not treat as confirmed.
A64: BRO | B64: Capital Expenditures | C64: 0.05 | D64: 0.06 | E64: 0.07 | F64: 0.08 | G64: 0.11 | H64: 0.13 | I64: https://www.sec.gov/Archives/edgar/data/79282/000119312526046984/bro-20251231.htm | J64: Needs review | K64: Historical and TTM values have not all been reconciled to the cash-flow statement; do not treat as confirmed.
A65: BRO | B65: Free Cash Flow | C65: =IFERROR(C63-C64,"") -> 0.65 | D65: =IFERROR(D63-D64,"") -> 0.76 | E65: =IFERROR(E63-E64,"") -> 0.88 | F65: =IFERROR(F63-F64,"") -> 0.97 | G65: =IFERROR(G63-G64,"") -> 1.29 | H65: =IFERROR(H63-H64,"") -> 1.52 | I65: Calculated | J65: Calculated — inputs require review | K65: Formula is live; output reliability depends on source inputs. See Audit_Log for source status.
A66: BRO | B66: Current Assets | C66: 5.2 | D66: 5.8 | E66: 6.4 | F66: 7.1 | G66: 8.9 | H66: 9.8 | I66: https://www.sec.gov/Archives/edgar/data/79282/000119312526046984/bro-20251231.htm | J66: Needs review | K66: Not independently reconciled to the corresponding balance-sheet line items in this pass. Ratios using this row are provisional.
A67: BRO | B67: Current Liabilities | C67: 3.8 | D67: 4.2 | E67: 4.6 | F67: 5.1 | G67: 6.3 | H67: 6.9 | I67: https://www.sec.gov/Archives/edgar/data/79282/000119312526046984/bro-20251231.htm | J67: Needs review | K67: Not independently reconciled to the corresponding balance-sheet line items in this pass. Ratios using this row are provisional.
A68: BRO | B68: Current Ratio | C68: =IFERROR(C66/C67,"") -> 1.3684211 | D68: =IFERROR(D66/D67,"") -> 1.3809524 | E68: =IFERROR(E66/E67,"") -> 1.3913043 | F68: =IFERROR(F66/F67,"") -> 1.3921569 | G68: =IFERROR(G66/G67,"") -> 1.4126984 | H68: =IFERROR(H66/H67,"") -> 1.4202899 | I68: Calculated | J68: Calculated — inputs require review | K68: Formula is live; output reliability depends on source inputs. See Audit_Log for source status.
A69: BRO | B69: Total Debt | C69: 2.8 | D69: 3.1 | E69: 3.4 | F69: 3.7 | G69: 4.5 | H69: 4.9 | I69: https://www.sec.gov/Archives/edgar/data/79282/000119312526046984/bro-20251231.htm | J69: Needs review | K69: Not independently reconciled to the corresponding balance-sheet line items in this pass. Ratios using this row are provisional.
A70: BRO | B70: Interest Expense | C70: 0.1 | D70: 0.11 | E70: 0.19 | F70: 0.193 | G70: 0.297 | H70: 0.17 | I70: https://www.sec.gov/Archives/edgar/data/79282/000119312526046984/bro-20251231.htm | J70: Partially verified | K70: FY2023–FY2025 verified only where updated; any blank/unchanged year, 2021–2022, and 2026_TTM require source-line review. Definitions can differ across issuers.
A71: BRO | B71: Interest Coverage Ratio | C71: =IFERROR(C60/C70,"") -> 7.5 | D71: =IFERROR(D60/D70,"") -> 8.1818182 | E71: =IFERROR(E60/E70,"") -> 7.0315789 | F71: =IFERROR(F60/F70,"") -> 7.7512953 | G71: =IFERROR(G60/G70,"") -> 5.6161616 | H71: =IFERROR(H60/H70,"") -> 10.882353 | I71: Calculated | J71: Calculated — inputs require review | K71: Formula is live; output reliability depends on source inputs. See Audit_Log for source status.

Sheet Stress_Test_Matrix
A1: Company | B1: Scenario | C1: Revenue Shock | D1: Stressed Revenue (USD bn) | E1: Stressed EBIT (USD bn) | F1: Stressed Interest Coverage (x) | G1: Illustrative Coverage Assessment | H1: DOL Assumption | I1: Formula / Scenario Meaning | J1: Baseline Period / Caveat | K1: Method Note | M1: Assumptions (inputs) | N1: Value
A2: WTW | B2: Base Case | C2: 0 | D2: =Financial_Metrics!G2*(1+C2) -> 9.708 | E2: =Financial_Metrics!G4*(1+H2*C2) -> 2.234 | F2: =IFERROR(E2/Financial_Metrics!G14,"") -> 8.5923077 | G2: =IF(F2="","Not assessed",IF(F2>=$N$3,"Illustrative buffer",IF(F2>=$N$4,"Pressure","High pressure"))) -> Illustrative buffer | H2: =$N$2 -> 2.5 | I2: Revenue = FY2025 revenue × (1 + shock); EBIT proxy = FY2025 EBIT × (1 + DOL × shock). | J2: FY2025 baseline; sensitivity analysis only, not a forecast. | K2: DOL = 2.5 is an explicit assumption. Coverage thresholds are illustrative, not validated credit ratings. | M2: DOL (degree of operating leverage) | N2: 2.5
A3: WTW | B3: Mild Stress | C3: -0.05 | D3: =Financial_Metrics!G2*(1+C3) -> 9.2226 | E3: =Financial_Metrics!G4*(1+H3*C3) -> 1.95475 | F3: =IFERROR(E3/Financial_Metrics!G14,"") -> 7.5182692 | G3: =IF(F3="","Not assessed",IF(F3>=$N$3,"Illustrative buffer",IF(F3>=$N$4,"Pressure","High pressure"))) -> Illustrative buffer | H3: =$N$2 -> 2.5 | I3: Revenue = FY2025 revenue × (1 + shock); EBIT proxy = FY2025 EBIT × (1 + DOL × shock). | J3: FY2025 baseline; sensitivity analysis only, not a forecast. | K3: DOL = 2.5 is an explicit assumption. Coverage thresholds are illustrative, not validated credit ratings. | M3: "Illustrative buffer" threshold (x) | N3: 5
A4: WTW | B4: Severe Stress | C4: -0.1 | D4: =Financial_Metrics!G2*(1+C4) -> 8.7372 | E4: =Financial_Metrics!G4*(1+H4*C4) -> 1.6755 | F4: =IFERROR(E4/Financial_Metrics!G14,"") -> 6.4442308 | G4: =IF(F4="","Not assessed",IF(F4>=$N$3,"Illustrative buffer",IF(F4>=$N$4,"Pressure","High pressure"))) -> Illustrative buffer | H4: =$N$2 -> 2.5 | I4: Revenue = FY2025 revenue × (1 + shock); EBIT proxy = FY2025 EBIT × (1 + DOL × shock). | J4: FY2025 baseline; sensitivity analysis only, not a forecast. | K4: DOL = 2.5 is an explicit assumption. Coverage thresholds are illustrative, not validated credit ratings. | M4: "Pressure" threshold (x) | N4: 2
A5: WTW | B5: Critical Shock | C5: -0.25 | D5: =Financial_Metrics!G2*(1+C5) -> 7.281 | E5: =Financial_Metrics!G4*(1+H5*C5) -> 0.83775 | F5: =IFERROR(E5/Financial_Metrics!G14,"") -> 3.2221154 | G5: =IF(F5="","Not assessed",IF(F5>=$N$3,"Illustrative buffer",IF(F5>=$N$4,"Pressure","High pressure"))) -> Pressure | H5: =$N$2 -> 2.5 | I5: Revenue = FY2025 revenue × (1 + shock); EBIT proxy = FY2025 EBIT × (1 + DOL × shock). | J5: FY2025 baseline; sensitivity analysis only, not a forecast. | K5: DOL = 2.5 is an explicit assumption. Coverage thresholds are illustrative, not validated credit ratings.
A6: Aon | B6: Base Case | C6: 0 | D6: =Financial_Metrics!G16*(1+C6) -> 17.181 | E6: =Financial_Metrics!G18*(1+H6*C6) -> 4.344 | F6: =IFERROR(E6/Financial_Metrics!G28,"") -> 5.3300613 | G6: =IF(F6="","Not assessed",IF(F6>=$N$3,"Illustrative buffer",IF(F6>=$N$4,"Pressure","High pressure"))) -> Illustrative buffer | H6: =$N$2 -> 2.5 | I6: Revenue = FY2025 revenue × (1 + shock); EBIT proxy = FY2025 EBIT × (1 + DOL × shock). | J6: FY2025 baseline; sensitivity analysis only, not a forecast. | K6: DOL = 2.5 is an explicit assumption. Coverage thresholds are illustrative, not validated credit ratings.
A7: Aon | B7: Mild Stress | C7: -0.05 | D7: =Financial_Metrics!G16*(1+C7) -> 16.32195 | E7: =Financial_Metrics!G18*(1+H7*C7) -> 3.801 | F7: =IFERROR(E7/Financial_Metrics!G28,"") -> 4.6638037 | G7: =IF(F7="","Not assessed",IF(F7>=$N$3,"Illustrative buffer",IF(F7>=$N$4,"Pressure","High pressure"))) -> Pressure | H7: =$N$2 -> 2.5 | I7: Revenue = FY2025 revenue × (1 + shock); EBIT proxy = FY2025 EBIT × (1 + DOL × shock). | J7: FY2025 baseline; sensitivity analysis only, not a forecast. | K7: DOL = 2.5 is an explicit assumption. Coverage thresholds are illustrative, not validated credit ratings.
A8: Aon | B8: Severe Stress | C8: -0.1 | D8: =Financial_Metrics!G16*(1+C8) -> 15.4629 | E8: =Financial_Metrics!G18*(1+H8*C8) -> 3.258 | F8: =IFERROR(E8/Financial_Metrics!G28,"") -> 3.997546 | G8: =IF(F8="","Not assessed",IF(F8>=$N$3,"Illustrative buffer",IF(F8>=$N$4,"Pressure","High pressure"))) -> Pressure | H8: =$N$2 -> 2.5 | I8: Revenue = FY2025 revenue × (1 + shock); EBIT proxy = FY2025 EBIT × (1 + DOL × shock). | J8: FY2025 baseline; sensitivity analysis only, not a forecast. | K8: DOL = 2.5 is an explicit assumption. Coverage thresholds are illustrative, not validated credit ratings.
A9: Aon | B9: Critical Shock | C9: -0.25 | D9: =Financial_Metrics!G16*(1+C9) -> 12.88575 | E9: =Financial_Metrics!G18*(1+H9*C9) -> 1.629 | F9: =IFERROR(E9/Financial_Metrics!G28,"") -> 1.998773 | G9: =IF(F9="","Not assessed",IF(F9>=$N$3,"Illustrative buffer",IF(F9>=$N$4,"Pressure","High pressure"))) -> High pressure | H9: =$N$2 -> 2.5 | I9: Revenue = FY2025 revenue × (1 + shock); EBIT proxy = FY2025 EBIT × (1 + DOL × shock). | J9: FY2025 baseline; sensitivity analysis only, not a forecast. | K9: DOL = 2.5 is an explicit assumption. Coverage thresholds are illustrative, not validated credit ratings.
A10: MMC | B10: Base Case | C10: 0 | D10: =Financial_Metrics!G30*(1+C10) -> 26.981 | E10: =Financial_Metrics!G32*(1+H10*C10) -> 6.223 | F10: =IFERROR(E10/Financial_Metrics!G42,"") -> 6.4822917 | G10: =IF(F10="","Not assessed",IF(F10>=$N$3,"Illustrative buffer",IF(F10>=$N$4,"Pressure","High pressure"))) -> Illustrative buffer | H10: =$N$2 -> 2.5 | I10: Revenue = FY2025 revenue × (1 + shock); EBIT proxy = FY2025 EBIT × (1 + DOL × shock). | J10: FY2025 baseline; sensitivity analysis only, not a forecast. | K10: DOL = 2.5 is an explicit assumption. Coverage thresholds are illustrative, not validated credit ratings.
A11: MMC | B11: Mild Stress | C11: -0.05 | D11: =Financial_Metrics!G30*(1+C11) -> 25.63195 | E11: =Financial_Metrics!G32*(1+H11*C11) -> 5.445125 | F11: =IFERROR(E11/Financial_Metrics!G42,"") -> 5.6720052 | G11: =IF(F11="","Not assessed",IF(F11>=$N$3,"Illustrative buffer",IF(F11>=$N$4,"Pressure","High pressure"))) -> Illustrative buffer | H11: =$N$2 -> 2.5 | I11: Revenue = FY2025 revenue × (1 + shock); EBIT proxy = FY2025 EBIT × (1 + DOL × shock). | J11: FY2025 baseline; sensitivity analysis only, not a forecast. | K11: DOL = 2.5 is an explicit assumption. Coverage thresholds are illustrative, not validated credit ratings.
A12: MMC | B12: Severe Stress | C12: -0.1 | D12: =Financial_Metrics!G30*(1+C12) -> 24.2829 | E12: =Financial_Metrics!G32*(1+H12*C12) -> 4.66725 | F12: =IFERROR(E12/Financial_Metrics!G42,"") -> 4.8617187 | G12: =IF(F12="","Not assessed",IF(F12>=$N$3,"Illustrative buffer",IF(F12>=$N$4,"Pressure","High pressure"))) -> Pressure | H12: =$N$2 -> 2.5 | I12: Revenue = FY2025 revenue × (1 + shock); EBIT proxy = FY2025 EBIT × (1 + DOL × shock). | J12: FY2025 baseline; sensitivity analysis only, not a forecast. | K12: DOL = 2.5 is an explicit assumption. Coverage thresholds are illustrative, not validated credit ratings.
A13: MMC | B13: Critical Shock | C13: -0.25 | D13: =Financial_Metrics!G30*(1+C13) -> 20.23575 | E13: =Financial_Metrics!G32*(1+H13*C13) -> 2.333625 | F13: =IFERROR(E13/Financial_Metrics!G42,"") -> 2.4308594 | G13: =IF(F13="","Not assessed",IF(F13>=$N$3,"Illustrative buffer",IF(F13>=$N$4,"Pressure","High pressure"))) -> Pressure | H13: =$N$2 -> 2.5 | I13: Revenue = FY2025 revenue × (1 + shock); EBIT proxy = FY2025 EBIT × (1 + DOL × shock). | J13: FY2025 baseline; sensitivity analysis only, not a forecast. | K13: DOL = 2.5 is an explicit assumption. Coverage thresholds are illustrative, not validated credit ratings.
A14: AJG | B14: Base Case | C14: 0 | D14: =Financial_Metrics!G44*(1+C14) -> 13.942 | E14: =Financial_Metrics!G46*(1+H14*C14) -> 2.51 | F14: =IFERROR(E14/Financial_Metrics!G56,"") -> 3.9280125 | G14: =IF(F14="","Not assessed",IF(F14>=$N$3,"Illustrative buffer",IF(F14>=$N$4,"Pressure","High pressure"))) -> Pressure | H14: =$N$2 -> 2.5 | I14: Revenue = FY2025 revenue × (1 + shock); EBIT proxy = FY2025 EBIT × (1 + DOL × shock). | J14: FY2025 baseline; sensitivity analysis only, not a forecast. | K14: DOL = 2.5 is an explicit assumption. Coverage thresholds are illustrative, not validated credit ratings.
A15: AJG | B15: Mild Stress | C15: -0.05 | D15: =Financial_Metrics!G44*(1+C15) -> 13.2449 | E15: =Financial_Metrics!G46*(1+H15*C15) -> 2.19625 | F15: =IFERROR(E15/Financial_Metrics!G56,"") -> 3.437011 | G15: =IF(F15="","Not assessed",IF(F15>=$N$3,"Illustrative buffer",IF(F15>=$N$4,"Pressure","High pressure"))) -> Pressure | H15: =$N$2 -> 2.5 | I15: Revenue = FY2025 revenue × (1 + shock); EBIT proxy = FY2025 EBIT × (1 + DOL × shock). | J15: FY2025 baseline; sensitivity analysis only, not a forecast. | K15: DOL = 2.5 is an explicit assumption. Coverage thresholds are illustrative, not validated credit ratings.
A16: AJG | B16: Severe Stress | C16: -0.1 | D16: =Financial_Metrics!G44*(1+C16) -> 12.5478 | E16: =Financial_Metrics!G46*(1+H16*C16) -> 1.8825 | F16: =IFERROR(E16/Financial_Metrics!G56,"") -> 2.9460094 | G16: =IF(F16="","Not assessed",IF(F16>=$N$3,"Illustrative buffer",IF(F16>=$N$4,"Pressure","High pressure"))) -> Pressure | H16: =$N$2 -> 2.5 | I16: Revenue = FY2025 revenue × (1 + shock); EBIT proxy = FY2025 EBIT × (1 + DOL × shock). | J16: FY2025 baseline; sensitivity analysis only, not a forecast. | K16: DOL = 2.5 is an explicit assumption. Coverage thresholds are illustrative, not validated credit ratings.
A17: AJG | B17: Critical Shock | C17: -0.25 | D17: =Financial_Metrics!G44*(1+C17) -> 10.4565 | E17: =Financial_Metrics!G46*(1+H17*C17) -> 0.94125 | F17: =IFERROR(E17/Financial_Metrics!G56,"") -> 1.4730047 | G17: =IF(F17="","Not assessed",IF(F17>=$N$3,"Illustrative buffer",IF(F17>=$N$4,"Pressure","High pressure"))) -> High pressure | H17: =$N$2 -> 2.5 | I17: Revenue = FY2025 revenue × (1 + shock); EBIT proxy = FY2025 EBIT × (1 + DOL × shock). | J17: FY2025 baseline; sensitivity analysis only, not a forecast. | K17: DOL = 2.5 is an explicit assumption. Coverage thresholds are illustrative, not validated credit ratings.
A18: BRO | B18: Base Case | C18: 0 | D18: =Financial_Metrics!G58*(1+C18) -> 5.902 | E18: =Financial_Metrics!G60*(1+H18*C18) -> 1.668 | F18: =IFERROR(E18/Financial_Metrics!G70,"") -> 5.6161616 | G18: =IF(F18="","Not assessed",IF(F18>=$N$3,"Illustrative buffer",IF(F18>=$N$4,"Pressure","High pressure"))) -> Illustrative buffer | H18: =$N$2 -> 2.5 | I18: Revenue = FY2025 revenue × (1 + shock); EBIT proxy = FY2025 EBIT × (1 + DOL × shock). | J18: FY2025 baseline; sensitivity analysis only, not a forecast. | K18: DOL = 2.5 is an explicit assumption. Coverage thresholds are illustrative, not validated credit ratings.
A19: BRO | B19: Mild Stress | C19: -0.05 | D19: =Financial_Metrics!G58*(1+C19) -> 5.6069 | E19: =Financial_Metrics!G60*(1+H19*C19) -> 1.4595 | F19: =IFERROR(E19/Financial_Metrics!G70,"") -> 4.9141414 | G19: =IF(F19="","Not assessed",IF(F19>=$N$3,"Illustrative buffer",IF(F19>=$N$4,"Pressure","High pressure"))) -> Pressure | H19: =$N$2 -> 2.5 | I19: Revenue = FY2025 revenue × (1 + shock); EBIT proxy = FY2025 EBIT × (1 + DOL × shock). | J19: FY2025 baseline; sensitivity analysis only, not a forecast. | K19: DOL = 2.5 is an explicit assumption. Coverage thresholds are illustrative, not validated credit ratings.
A20: BRO | B20: Severe Stress | C20: -0.1 | D20: =Financial_Metrics!G58*(1+C20) -> 5.3118 | E20: =Financial_Metrics!G60*(1+H20*C20) -> 1.251 | F20: =IFERROR(E20/Financial_Metrics!G70,"") -> 4.2121212 | G20: =IF(F20="","Not assessed",IF(F20>=$N$3,"Illustrative buffer",IF(F20>=$N$4,"Pressure","High pressure"))) -> Pressure | H20: =$N$2 -> 2.5 | I20: Revenue = FY2025 revenue × (1 + shock); EBIT proxy = FY2025 EBIT × (1 + DOL × shock). | J20: FY2025 baseline; sensitivity analysis only, not a forecast. | K20: DOL = 2.5 is an explicit assumption. Coverage thresholds are illustrative, not validated credit ratings.
A21: BRO | B21: Critical Shock | C21: -0.25 | D21: =Financial_Metrics!G58*(1+C21) -> 4.4265 | E21: =Financial_Metrics!G60*(1+H21*C21) -> 0.6255 | F21: =IFERROR(E21/Financial_Metrics!G70,"") -> 2.1060606 | G21: =IF(F21="","Not assessed",IF(F21>=$N$3,"Illustrative buffer",IF(F21>=$N$4,"Pressure","High pressure"))) -> Pressure | H21: =$N$2 -> 2.5 | I21: Revenue = FY2025 revenue × (1 + shock); EBIT proxy = FY2025 EBIT × (1 + DOL × shock). | J21: FY2025 baseline; sensitivity analysis only, not a forecast. | K21: DOL = 2.5 is an explicit assumption. Coverage thresholds are illustrative, not validated credit ratings.

Sheet Financial_Ratios
A1: Company | B1: Period | C1: Current Ratio | D1: Interest Coverage Ratio | E1: Debt-to-Equity | F1: Debt-to-EBITDA | G1: Free Cash Flow Margin | H1: Operating Cash Flow / Total Debt | I1: Formula / Interpretation | J1: Limitations / Status | K1: Operating Profit Margin (EBIT / Revenue)
A2: WTW | B2: 2021 | C2: =IFERROR(Financial_Metrics!C10/Financial_Metrics!C11,"") -> 1.0714286 | D2: =IFERROR(Financial_Metrics!C4/Financial_Metrics!C14,"") -> 6.25 | E2: N/A — equity data unavailable | F2: N/A — EBITDA inputs unavailable | G2: =IFERROR(Financial_Metrics!C9/Financial_Metrics!C2,"") -> 0.20333333 | H2: =IFERROR(Financial_Metrics!C7/Financial_Metrics!C13,"") -> 0.38433515 | I2: Current ratio = current assets / current liabilities; coverage = EBIT / interest expense; FCF margin = FCF / revenue; OCF/debt = operating cash flow / total debt. | J2: Provisional: formula-driven, but source inputs for balance-sheet and cash-flow ratios still need reconciliation. Debt-to-Equity and Debt-to-EBITDA unavailable. | K2: =IFERROR(Financial_Metrics!C4/Financial_Metrics!C2,"") -> 0.19444444
A3: WTW | B3: 2022 | C3: =IFERROR(Financial_Metrics!D10/Financial_Metrics!D11,"") -> 1.0696056 | D3: =IFERROR(Financial_Metrics!D4/Financial_Metrics!D14,"") -> 6.0333333 | E3: N/A — equity data unavailable | F3: N/A — EBITDA inputs unavailable | G3: =IFERROR(Financial_Metrics!D9/Financial_Metrics!D2,"") -> 0.075535513 | H3: =IFERROR(Financial_Metrics!D7/Financial_Metrics!D13,"") -> 0.1770073 | I3: Current ratio = current assets / current liabilities; coverage = EBIT / interest expense; FCF margin = FCF / revenue; OCF/debt = operating cash flow / total debt. | J3: Provisional: formula-driven, but source inputs for balance-sheet and cash-flow ratios still need reconciliation. Debt-to-Equity and Debt-to-EBITDA unavailable. | K3: =IFERROR(Financial_Metrics!D4/Financial_Metrics!D2,"") -> 0.20405862
A4: WTW | B4: 2023 | C4: =IFERROR(Financial_Metrics!E10/Financial_Metrics!E11,"") -> 1.0603318 | D4: =IFERROR(Financial_Metrics!E4/Financial_Metrics!E14,"") -> 5.8085106 | E4: N/A — equity data unavailable | F4: N/A — EBITDA inputs unavailable | G4: =IFERROR(Financial_Metrics!E9/Financial_Metrics!E2,"") -> 0.1163134 | H4: =IFERROR(Financial_Metrics!E7/Financial_Metrics!E13,"") -> 0.22605042 | I4: Current ratio = current assets / current liabilities; coverage = EBIT / interest expense; FCF margin = FCF / revenue; OCF/debt = operating cash flow / total debt. | J4: Provisional: formula-driven, but source inputs for balance-sheet and cash-flow ratios still need reconciliation. Debt-to-Equity and Debt-to-EBITDA unavailable. | K4: =IFERROR(Financial_Metrics!E4/Financial_Metrics!E2,"") -> 0.14394179
A5: WTW | B5: 2024 | C5: =IFERROR(Financial_Metrics!F10/Financial_Metrics!F11,"") -> 1.1989998 | D5: =IFERROR(Financial_Metrics!F4/Financial_Metrics!F14,"") -> 2.3840304 | E5: N/A — equity data unavailable | F5: N/A — EBITDA inputs unavailable | G5: =IFERROR(Financial_Metrics!F9/Financial_Metrics!F2,"") -> 0.12759315 | H5: =IFERROR(Financial_Metrics!F7/Financial_Metrics!F13,"") -> 0.25501771 | I5: Current ratio = current assets / current liabilities; coverage = EBIT / interest expense; FCF margin = FCF / revenue; OCF/debt = operating cash flow / total debt. | J5: Provisional: formula-driven, but source inputs for balance-sheet and cash-flow ratios still need reconciliation. Debt-to-Equity and Debt-to-EBITDA unavailable. | K5: =IFERROR(Financial_Metrics!F4/Financial_Metrics!F2,"") -> 0.063141994
A6: WTW | B6: 2025 | C6: =IFERROR(Financial_Metrics!G10/Financial_Metrics!G11,"") -> 1.2049414 | D6: =IFERROR(Financial_Metrics!G4/Financial_Metrics!G14,"") -> 8.5923077 | E6: N/A — equity data unavailable | F6: N/A — EBITDA inputs unavailable | G6: =IFERROR(Financial_Metrics!G9/Financial_Metrics!G2,"") -> 0.1592501 | H6: =IFERROR(Financial_Metrics!G7/Financial_Metrics!G13,"") -> 0.25713458 | I6: Current ratio = current assets / current liabilities; coverage = EBIT / interest expense; FCF margin = FCF / revenue; OCF/debt = operating cash flow / total debt. | J6: Provisional: formula-driven, but source inputs for balance-sheet and cash-flow ratios still need reconciliation. Debt-to-Equity and Debt-to-EBITDA unavailable. | K6: =IFERROR(Financial_Metrics!G4/Financial_Metrics!G2,"") -> 0.23011949
A7: WTW | B7: 2026_TTM | C7: =IFERROR(Financial_Metrics!H10/Financial_Metrics!H11,"") -> 1.0983607 | D7: =IFERROR(Financial_Metrics!H4/Financial_Metrics!H14,"") -> 5.2058824 | E7: N/A — equity data unavailable | F7: N/A — EBITDA inputs unavailable | G7: =IFERROR(Financial_Metrics!H9/Financial_Metrics!H2,"") -> 0.16732673 | H7: =IFERROR(Financial_Metrics!H7/Financial_Metrics!H13,"") -> 0.28732394 | I7: Current ratio = current assets / current liabilities; coverage = EBIT / interest expense; FCF margin = FCF / revenue; OCF/debt = operating cash flow / total debt. | J7: Provisional: formula-driven, but source inputs for balance-sheet and cash-flow ratios still need reconciliation. Debt-to-Equity and Debt-to-EBITDA unavailable. | K7: =IFERROR(Financial_Metrics!H4/Financial_Metrics!H2,"") -> 0.17524752
A8: Aon | B8: 2021 | C8: =IFERROR(Financial_Metrics!C24/Financial_Metrics!C25,"") -> 0.92763158 | D8: =IFERROR(Financial_Metrics!C18/Financial_Metrics!C28,"") -> 7.3809524 | E8: N/A — equity data unavailable | F8: N/A — EBITDA inputs unavailable | G8: =IFERROR(Financial_Metrics!C23/Financial_Metrics!C16,"") -> 0.18032787 | H8: =IFERROR(Financial_Metrics!C21/Financial_Metrics!C27,"") -> 0.23214286 | I8: Current ratio = current assets / current liabilities; coverage = EBIT / interest expense; FCF margin = FCF / revenue; OCF/debt = operating cash flow / total debt. | J8: Provisional: formula-driven, but source inputs for balance-sheet and cash-flow ratios still need reconciliation. Debt-to-Equity and Debt-to-EBITDA unavailable. | K8: =IFERROR(Financial_Metrics!C18/Financial_Metrics!C16,"") -> 0.25409836
A9: Aon | B9: 2022 | C9: =IFERROR(Financial_Metrics!D24/Financial_Metrics!D25,"") -> 0.93548387 | D9: =IFERROR(Financial_Metrics!D18/Financial_Metrics!D28,"") -> 7.1111111 | E9: N/A — equity data unavailable | F9: N/A — EBITDA inputs unavailable | G9: =IFERROR(Financial_Metrics!D23/Financial_Metrics!D16,"") -> 0.188 | H9: =IFERROR(Financial_Metrics!D21/Financial_Metrics!D27,"") -> 0.24347826 | I9: Current ratio = current assets / current liabilities; coverage = EBIT / interest expense; FCF margin = FCF / revenue; OCF/debt = operating cash flow / total debt. | J9: Provisional: formula-driven, but source inputs for balance-sheet and cash-flow ratios still need reconciliation. Debt-to-Equity and Debt-to-EBITDA unavailable. | K9: =IFERROR(Financial_Metrics!D18/Financial_Metrics!D16,"") -> 0.256
A10: Aon | B10: 2023 | C10: =IFERROR(Financial_Metrics!E24/Financial_Metrics!E25,"") -> 0.93209877 | D10: =IFERROR(Financial_Metrics!E18/Financial_Metrics!E28,"") -> 7.8854167 | E10: N/A — equity data unavailable | F10: N/A — EBITDA inputs unavailable | G10: =IFERROR(Financial_Metrics!E23/Financial_Metrics!E16,"") -> 0.19437799 | H10: =IFERROR(Financial_Metrics!E21/Financial_Metrics!E27,"") -> 0.26271186 | I10: Current ratio = current assets / current liabilities; coverage = EBIT / interest expense; FCF margin = FCF / revenue; OCF/debt = operating cash flow / total debt. | J10: Provisional: formula-driven, but source inputs for balance-sheet and cash-flow ratios still need reconciliation. Debt-to-Equity and Debt-to-EBITDA unavailable. | K10: =IFERROR(Financial_Metrics!E18/Financial_Metrics!E16,"") -> 0.2829695
A11: Aon | B11: 2024 | C11: =IFERROR(Financial_Metrics!F24/Financial_Metrics!F25,"") -> 0.95757576 | D11: =IFERROR(Financial_Metrics!F18/Financial_Metrics!F28,"") -> 4.8667513 | E11: N/A — equity data unavailable | F11: N/A — EBITDA inputs unavailable | G11: =IFERROR(Financial_Metrics!F23/Financial_Metrics!F16,"") -> 0.16881131 | H11: =IFERROR(Financial_Metrics!F21/Financial_Metrics!F27,"") -> 0.26446281 | I11: Current ratio = current assets / current liabilities; coverage = EBIT / interest expense; FCF margin = FCF / revenue; OCF/debt = operating cash flow / total debt. | J11: Provisional: formula-driven, but source inputs for balance-sheet and cash-flow ratios still need reconciliation. Debt-to-Equity and Debt-to-EBITDA unavailable. | K11: =IFERROR(Financial_Metrics!F18/Financial_Metrics!F16,"") -> 0.24429864
A12: Aon | B12: 2025 | C12: =IFERROR(Financial_Metrics!G24/Financial_Metrics!G25,"") -> 0.95266272 | D12: =IFERROR(Financial_Metrics!G18/Financial_Metrics!G28,"") -> 5.3300613 | E12: N/A — equity data unavailable | F12: N/A — EBITDA inputs unavailable | G12: =IFERROR(Financial_Metrics!G23/Financial_Metrics!G16,"") -> 0.16588091 | H12: =IFERROR(Financial_Metrics!G21/Financial_Metrics!G27,"") -> 0.24137931 | I12: Current ratio = current assets / current liabilities; coverage = EBIT / interest expense; FCF margin = FCF / revenue; OCF/debt = operating cash flow / total debt. | J12: Provisional: formula-driven, but source inputs for balance-sheet and cash-flow ratios still need reconciliation. Debt-to-Equity and Debt-to-EBITDA unavailable. | K12: =IFERROR(Financial_Metrics!G18/Financial_Metrics!G16,"") -> 0.25283744
A13: Aon | B13: 2026_TTM | C13: =IFERROR(Financial_Metrics!H24/Financial_Metrics!H25,"") -> 0.96491228 | D13: =IFERROR(Financial_Metrics!H18/Financial_Metrics!H28,"") -> 8.0769231 | E13: N/A — equity data unavailable | F13: N/A — EBITDA inputs unavailable | G13: =IFERROR(Financial_Metrics!H23/Financial_Metrics!H16,"") -> 0.17463026 | H13: =IFERROR(Financial_Metrics!H21/Financial_Metrics!H27,"") -> 0.23944549 | I13: Current ratio = current assets / current liabilities; coverage = EBIT / interest expense; FCF margin = FCF / revenue; OCF/debt = operating cash flow / total debt. | J13: Provisional: formula-driven, but source inputs for balance-sheet and cash-flow ratios still need reconciliation. Debt-to-Equity and Debt-to-EBITDA unavailable. | K13: =IFERROR(Financial_Metrics!H18/Financial_Metrics!H16,"") -> 0.23890785
A14: MMC | B14: 2021 | C14: =IFERROR(Financial_Metrics!C38/Financial_Metrics!C39,"") -> 1.1333333 | D14: =IFERROR(Financial_Metrics!C32/Financial_Metrics!C42,"") -> 8.6 | E14: N/A — equity data unavailable | F14: N/A — EBITDA inputs unavailable | G14: =IFERROR(Financial_Metrics!C37/Financial_Metrics!C30,"") -> 0.1715439 | H14: =IFERROR(Financial_Metrics!C35/Financial_Metrics!C41,"") -> 0.34210526 | I14: Current ratio = current assets / current liabilities; coverage = EBIT / interest expense; FCF margin = FCF / revenue; OCF/debt = operating cash flow / total debt. | J14: Provisional: formula-driven, but source inputs for balance-sheet and cash-flow ratios still need reconciliation. Debt-to-Equity and Debt-to-EBITDA unavailable. | K14: =IFERROR(Financial_Metrics!C32/Financial_Metrics!C30,"") -> 0.21695257
A15: MMC | B15: 2022 | C15: =IFERROR(Financial_Metrics!D38/Financial_Metrics!D39,"") -> 1.1641791 | D15: =IFERROR(Financial_Metrics!D32/Financial_Metrics!D42,"") -> 8.8461538 | E15: N/A — equity data unavailable | F15: N/A — EBITDA inputs unavailable | G15: =IFERROR(Financial_Metrics!D37/Financial_Metrics!D30,"") -> 0.1763285 | H15: =IFERROR(Financial_Metrics!D35/Financial_Metrics!D41,"") -> 0.35294118 | I15: Current ratio = current assets / current liabilities; coverage = EBIT / interest expense; FCF margin = FCF / revenue; OCF/debt = operating cash flow / total debt. | J15: Provisional: formula-driven, but source inputs for balance-sheet and cash-flow ratios still need reconciliation. Debt-to-Equity and Debt-to-EBITDA unavailable. | K15: =IFERROR(Financial_Metrics!D32/Financial_Metrics!D30,"") -> 0.22222222
A16: MMC | B16: 2023 | C16: =IFERROR(Financial_Metrics!E38/Financial_Metrics!E39,"") -> 1.1643192 | D16: =IFERROR(Financial_Metrics!E32/Financial_Metrics!E42,"") -> 9.1384083 | E16: N/A — equity data unavailable | F16: N/A — EBITDA inputs unavailable | G16: =IFERROR(Financial_Metrics!E37/Financial_Metrics!E30,"") -> 0.17593244 | H16: =IFERROR(Financial_Metrics!E35/Financial_Metrics!E41,"") -> 0.37398374 | I16: Current ratio = current assets / current liabilities; coverage = EBIT / interest expense; FCF margin = FCF / revenue; OCF/debt = operating cash flow / total debt. | J16: Provisional: formula-driven, but source inputs for balance-sheet and cash-flow ratios still need reconciliation. Debt-to-Equity and Debt-to-EBITDA unavailable. | K16: =IFERROR(Financial_Metrics!E32/Financial_Metrics!E30,"") -> 0.23231879
A17: MMC | B17: 2024 | C17: =IFERROR(Financial_Metrics!F38/Financial_Metrics!F39,"") -> 1.1651786 | D17: =IFERROR(Financial_Metrics!F32/Financial_Metrics!F42,"") -> 8.31 | E17: N/A — equity data unavailable | F17: N/A — EBITDA inputs unavailable | G17: =IFERROR(Financial_Metrics!F37/Financial_Metrics!F30,"") -> 0.17376727 | H17: =IFERROR(Financial_Metrics!F35/Financial_Metrics!F41,"") -> 0.3828125 | I17: Current ratio = current assets / current liabilities; coverage = EBIT / interest expense; FCF margin = FCF / revenue; OCF/debt = operating cash flow / total debt. | J17: Provisional: formula-driven, but source inputs for balance-sheet and cash-flow ratios still need reconciliation. Debt-to-Equity and Debt-to-EBITDA unavailable. | K17: =IFERROR(Financial_Metrics!F32/Financial_Metrics!F30,"") -> 0.23783629
A18: MMC | B18: 2025 | C18: =IFERROR(Financial_Metrics!G38/Financial_Metrics!G39,"") -> 1.1904762 | D18: =IFERROR(Financial_Metrics!G32/Financial_Metrics!G42,"") -> 6.4822917 | E18: N/A — equity data unavailable | F18: N/A — EBITDA inputs unavailable | G18: =IFERROR(Financial_Metrics!G37/Financial_Metrics!G30,"") -> 0.17049035 | H18: =IFERROR(Financial_Metrics!G35/Financial_Metrics!G41,"") -> 0.39552239 | I18: Current ratio = current assets / current liabilities; coverage = EBIT / interest expense; FCF margin = FCF / revenue; OCF/debt = operating cash flow / total debt. | J18: Provisional: formula-driven, but source inputs for balance-sheet and cash-flow ratios still need reconciliation. Debt-to-Equity and Debt-to-EBITDA unavailable. | K18: =IFERROR(Financial_Metrics!G32/Financial_Metrics!G30,"") -> 0.23064379
A19: MMC | B19: 2026_TTM | C19: =IFERROR(Financial_Metrics!H38/Financial_Metrics!H39,"") -> 1.1942149 | D19: =IFERROR(Financial_Metrics!H32/Financial_Metrics!H42,"") -> 10.322581 | E19: N/A — equity data unavailable | F19: N/A — EBITDA inputs unavailable | G19: =IFERROR(Financial_Metrics!H37/Financial_Metrics!H30,"") -> 0.17960644 | H19: =IFERROR(Financial_Metrics!H35/Financial_Metrics!H41,"") -> 0.41134752 | I19: Current ratio = current assets / current liabilities; coverage = EBIT / interest expense; FCF margin = FCF / revenue; OCF/debt = operating cash flow / total debt. | J19: Provisional: formula-driven, but source inputs for balance-sheet and cash-flow ratios still need reconciliation. Debt-to-Equity and Debt-to-EBITDA unavailable. | K19: =IFERROR(Financial_Metrics!H32/Financial_Metrics!H30,"") -> 0.22898032
A20: AJG | B20: 2021 | C20: =IFERROR(Financial_Metrics!C52/Financial_Metrics!C53,"") -> 1.2 | D20: =IFERROR(Financial_Metrics!C46/Financial_Metrics!C56,"") -> 7 | E20: N/A — equity data unavailable | F20: N/A — EBITDA inputs unavailable | G20: =IFERROR(Financial_Metrics!C51/Financial_Metrics!C44,"") -> 0.13801757 | H20: =IFERROR(Financial_Metrics!C49/Financial_Metrics!C55,"") -> 0.24509804 | I20: Current ratio = current assets / current liabilities; coverage = EBIT / interest expense; FCF margin = FCF / revenue; OCF/debt = operating cash flow / total debt. | J20: Provisional: formula-driven, but source inputs for balance-sheet and cash-flow ratios still need reconciliation. Debt-to-Equity and Debt-to-EBITDA unavailable. | K20: =IFERROR(Financial_Metrics!C46/Financial_Metrics!C44,"") -> 0.17565872
A21: AJG | B21: 2022 | C21: =IFERROR(Financial_Metrics!D52/Financial_Metrics!D53,"") -> 1.2391304 | D21: =IFERROR(Financial_Metrics!D46/Financial_Metrics!D56,"") -> 7.0454545 | E21: N/A — equity data unavailable | F21: N/A — EBITDA inputs unavailable | G21: =IFERROR(Financial_Metrics!D51/Financial_Metrics!D44,"") -> 0.1452381 | H21: =IFERROR(Financial_Metrics!D49/Financial_Metrics!D55,"") -> 0.25925926 | I21: Current ratio = current assets / current liabilities; coverage = EBIT / interest expense; FCF margin = FCF / revenue; OCF/debt = operating cash flow / total debt. | J21: Provisional: formula-driven, but source inputs for balance-sheet and cash-flow ratios still need reconciliation. Debt-to-Equity and Debt-to-EBITDA unavailable. | K21: =IFERROR(Financial_Metrics!D46/Financial_Metrics!D44,"") -> 0.18452381
A22: AJG | B22: 2023 | C22: =IFERROR(Financial_Metrics!E52/Financial_Metrics!E53,"") -> 1.2307692 | D22: =IFERROR(Financial_Metrics!E46/Financial_Metrics!E56,"") -> 5.928 | E22: N/A — equity data unavailable | F22: N/A — EBITDA inputs unavailable | G22: =IFERROR(Financial_Metrics!E51/Financial_Metrics!E44,"") -> 0.14694202 | H22: =IFERROR(Financial_Metrics!E49/Financial_Metrics!E55,"") -> 0.27419355 | I22: Current ratio = current assets / current liabilities; coverage = EBIT / interest expense; FCF margin = FCF / revenue; OCF/debt = operating cash flow / total debt. | J22: Provisional: formula-driven, but source inputs for balance-sheet and cash-flow ratios still need reconciliation. Debt-to-Equity and Debt-to-EBITDA unavailable. | K22: =IFERROR(Financial_Metrics!E46/Financial_Metrics!E44,"") -> 0.14714059
A23: AJG | B23: 2024 | C23: =IFERROR(Financial_Metrics!F52/Financial_Metrics!F53,"") -> 1.226087 | D23: =IFERROR(Financial_Metrics!F46/Financial_Metrics!F56,"") -> 5.9212598 | E23: N/A — equity data unavailable | F23: N/A — EBITDA inputs unavailable | G23: =IFERROR(Financial_Metrics!F51/Financial_Metrics!F44,"") -> 0.12808308 | H23: =IFERROR(Financial_Metrics!F49/Financial_Metrics!F55,"") -> 0.25 | I23: Current ratio = current assets / current liabilities; coverage = EBIT / interest expense; FCF margin = FCF / revenue; OCF/debt = operating cash flow / total debt. | J23: Provisional: formula-driven, but source inputs for balance-sheet and cash-flow ratios still need reconciliation. Debt-to-Equity and Debt-to-EBITDA unavailable. | K23: =IFERROR(Financial_Metrics!F46/Financial_Metrics!F44,"") -> 0.19524016
A24: AJG | B24: 2025 | C24: =IFERROR(Financial_Metrics!G52/Financial_Metrics!G53,"") -> 1.25 | D24: =IFERROR(Financial_Metrics!G46/Financial_Metrics!G56,"") -> 3.9280125 | E24: N/A — equity data unavailable | F24: N/A — EBITDA inputs unavailable | G24: =IFERROR(Financial_Metrics!G51/Financial_Metrics!G44,"") -> 0.15062401 | H24: =IFERROR(Financial_Metrics!G49/Financial_Metrics!G55,"") -> 0.30379747 | I24: Current ratio = current assets / current liabilities; coverage = EBIT / interest expense; FCF margin = FCF / revenue; OCF/debt = operating cash flow / total debt. | J24: Provisional: formula-driven, but source inputs for balance-sheet and cash-flow ratios still need reconciliation. Debt-to-Equity and Debt-to-EBITDA unavailable. | K24: =IFERROR(Financial_Metrics!G46/Financial_Metrics!G44,"") -> 0.18003156
A25: AJG | B25: 2026_TTM | C25: =IFERROR(Financial_Metrics!H52/Financial_Metrics!H53,"") -> 1.2465753 | D25: =IFERROR(Financial_Metrics!H46/Financial_Metrics!H56,"") -> 8.6111111 | E25: N/A — equity data unavailable | F25: N/A — EBITDA inputs unavailable | G25: =IFERROR(Financial_Metrics!H51/Financial_Metrics!H44,"") -> 0.15873016 | H25: =IFERROR(Financial_Metrics!H49/Financial_Metrics!H55,"") -> 0.32758621 | I25: Current ratio = current assets / current liabilities; coverage = EBIT / interest expense; FCF margin = FCF / revenue; OCF/debt = operating cash flow / total debt. | J25: Provisional: formula-driven, but source inputs for balance-sheet and cash-flow ratios still need reconciliation. Debt-to-Equity and Debt-to-EBITDA unavailable. | K25: =IFERROR(Financial_Metrics!H46/Financial_Metrics!H44,"") -> 0.1968254
A26: BRO | B26: 2021 | C26: =IFERROR(Financial_Metrics!C66/Financial_Metrics!C67,"") -> 1.3684211 | D26: =IFERROR(Financial_Metrics!C60/Financial_Metrics!C70,"") -> 7.5 | E26: N/A — equity data unavailable | F26: N/A — EBITDA inputs unavailable | G26: =IFERROR(Financial_Metrics!C65/Financial_Metrics!C58,"") -> 0.21311475 | H26: =IFERROR(Financial_Metrics!C63/Financial_Metrics!C69,"") -> 0.25 | I26: Current ratio = current assets / current liabilities; coverage = EBIT / interest expense; FCF margin = FCF / revenue; OCF/debt = operating cash flow / total debt. | J26: Provisional: formula-driven, but source inputs for balance-sheet and cash-flow ratios still need reconciliation. Debt-to-Equity and Debt-to-EBITDA unavailable. | K26: =IFERROR(Financial_Metrics!C60/Financial_Metrics!C58,"") -> 0.24590164
A27: BRO | B27: 2022 | C27: =IFERROR(Financial_Metrics!D66/Financial_Metrics!D67,"") -> 1.3809524 | D27: =IFERROR(Financial_Metrics!D60/Financial_Metrics!D70,"") -> 8.1818182 | E27: N/A — equity data unavailable | F27: N/A — EBITDA inputs unavailable | G27: =IFERROR(Financial_Metrics!D65/Financial_Metrics!D58,"") -> 0.21714286 | H27: =IFERROR(Financial_Metrics!D63/Financial_Metrics!D69,"") -> 0.26451613 | I27: Current ratio = current assets / current liabilities; coverage = EBIT / interest expense; FCF margin = FCF / revenue; OCF/debt = operating cash flow / total debt. | J27: Provisional: formula-driven, but source inputs for balance-sheet and cash-flow ratios still need reconciliation. Debt-to-Equity and Debt-to-EBITDA unavailable. | K27: =IFERROR(Financial_Metrics!D60/Financial_Metrics!D58,"") -> 0.25714286
A28: BRO | B28: 2023 | C28: =IFERROR(Financial_Metrics!E66/Financial_Metrics!E67,"") -> 1.3913043 | D28: =IFERROR(Financial_Metrics!E60/Financial_Metrics!E70,"") -> 7.0315789 | E28: N/A — equity data unavailable | F28: N/A — EBITDA inputs unavailable | G28: =IFERROR(Financial_Metrics!E65/Financial_Metrics!E58,"") -> 0.20671835 | H28: =IFERROR(Financial_Metrics!E63/Financial_Metrics!E69,"") -> 0.27941176 | I28: Current ratio = current assets / current liabilities; coverage = EBIT / interest expense; FCF margin = FCF / revenue; OCF/debt = operating cash flow / total debt. | J28: Provisional: formula-driven, but source inputs for balance-sheet and cash-flow ratios still need reconciliation. Debt-to-Equity and Debt-to-EBITDA unavailable. | K28: =IFERROR(Financial_Metrics!E60/Financial_Metrics!E58,"") -> 0.31383603
A29: BRO | B29: 2024 | C29: =IFERROR(Financial_Metrics!F66/Financial_Metrics!F67,"") -> 1.3921569 | D29: =IFERROR(Financial_Metrics!F60/Financial_Metrics!F70,"") -> 7.7512953 | E29: N/A — equity data unavailable | F29: N/A — EBITDA inputs unavailable | G29: =IFERROR(Financial_Metrics!F65/Financial_Metrics!F58,"") -> 0.20187305 | H29: =IFERROR(Financial_Metrics!F63/Financial_Metrics!F69,"") -> 0.28378378 | I29: Current ratio = current assets / current liabilities; coverage = EBIT / interest expense; FCF margin = FCF / revenue; OCF/debt = operating cash flow / total debt. | J29: Provisional: formula-driven, but source inputs for balance-sheet and cash-flow ratios still need reconciliation. Debt-to-Equity and Debt-to-EBITDA unavailable. | K29: =IFERROR(Financial_Metrics!F60/Financial_Metrics!F58,"") -> 0.31134235
A30: BRO | B30: 2025 | C30: =IFERROR(Financial_Metrics!G66/Financial_Metrics!G67,"") -> 1.4126984 | D30: =IFERROR(Financial_Metrics!G60/Financial_Metrics!G70,"") -> 5.6161616 | E30: N/A — equity data unavailable | F30: N/A — EBITDA inputs unavailable | G30: =IFERROR(Financial_Metrics!G65/Financial_Metrics!G58,"") -> 0.21856998 | H30: =IFERROR(Financial_Metrics!G63/Financial_Metrics!G69,"") -> 0.31111111 | I30: Current ratio = current assets / current liabilities; coverage = EBIT / interest expense; FCF margin = FCF / revenue; OCF/debt = operating cash flow / total debt. | J30: Provisional: formula-driven, but source inputs for balance-sheet and cash-flow ratios still need reconciliation. Debt-to-Equity and Debt-to-EBITDA unavailable. | K30: =IFERROR(Financial_Metrics!G60/Financial_Metrics!G58,"") -> 0.28261606
A31: BRO | B31: 2026_TTM | C31: =IFERROR(Financial_Metrics!H66/Financial_Metrics!H67,"") -> 1.4202899 | D31: =IFERROR(Financial_Metrics!H60/Financial_Metrics!H70,"") -> 10.882353 | E31: N/A — equity data unavailable | F31: N/A — EBITDA inputs unavailable | G31: =IFERROR(Financial_Metrics!H65/Financial_Metrics!H58,"") -> 0.22822823 | H31: =IFERROR(Financial_Metrics!H63/Financial_Metrics!H69,"") -> 0.33673469 | I31: Current ratio = current assets / current liabilities; coverage = EBIT / interest expense; FCF margin = FCF / revenue; OCF/debt = operating cash flow / total debt. | J31: Provisional: formula-driven, but source inputs for balance-sheet and cash-flow ratios still need reconciliation. Debt-to-Equity and Debt-to-EBITDA unavailable. | K31: =IFERROR(Financial_Metrics!H60/Financial_Metrics!H58,"") -> 0.27777778

Sheet Peer_Comparison
A1: Company | B1: FY2025 Revenue (USD bn) | C1: FY2025 EBIT (USD bn) | D1: FY2025 Net Income (USD bn) | E1: Net Profit Margin | F1: Current Ratio | G1: Debt / Revenue | H1: Operating Cash Flow (USD bn) | I1: Free Cash Flow (USD bn) | J1: FCF Margin | K1: Data Status / Caveat | L1: Mild Stress EBIT (USD bn) | M1: Severe Stress EBIT (USD bn) | N1: Severe Stress Coverage (x) | O1: Strength / Risk Note | P1: Source Note
A2: WTW | B2: =Financial_Metrics!G2 -> 9.708 | C2: =Financial_Metrics!G4 -> 2.234 | D2: =Financial_Metrics!G5 -> 1.605 | E2: =IFERROR(D2/B2,"") -> 0.16532756 | F2: =Financial_Metrics!G12 -> 1.2049414 | G2: =IFERROR(Financial_Metrics!G13/B2,"") -> 0.71106304 | H2: =Financial_Metrics!G7 -> 1.775 | I2: =Financial_Metrics!G9 -> 1.546 | J2: =IFERROR(I2/B2,"") -> 0.1592501 | K2: FY2025 reported values linked from Financial_Metrics; other linked ratios remain provisional where source inputs are unverified. | L2: =Stress_Test_Matrix!E3 -> 1.95475 | M2: =Stress_Test_Matrix!E4 -> 1.6755 | N2: =Stress_Test_Matrix!F4 -> 6.4442308 | O2: Peer comparison is descriptive; verify source inputs and definitions before drawing investment conclusions. | P2: Source links are in Financial_Metrics; figures are not independently audited in this correction.
A3: Aon | B3: =Financial_Metrics!G16 -> 17.181 | C3: =Financial_Metrics!G18 -> 4.344 | D3: =Financial_Metrics!G19 -> 3.695 | E3: =IFERROR(D3/B3,"") -> 0.21506315 | F3: =Financial_Metrics!G26 -> 0.95266272 | G3: =IFERROR(Financial_Metrics!G27/B3,"") -> 0.84395553 | H3: =Financial_Metrics!G21 -> 3.5 | I3: =Financial_Metrics!G23 -> 2.85 | J3: =IFERROR(I3/B3,"") -> 0.16588091 | K3: FY2025 reported values linked from Financial_Metrics; other linked ratios remain provisional where source inputs are unverified. | L3: =Stress_Test_Matrix!E7 -> 3.801 | M3: =Stress_Test_Matrix!E8 -> 3.258 | N3: =Stress_Test_Matrix!F8 -> 3.997546 | O3: Peer comparison is descriptive; verify source inputs and definitions before drawing investment conclusions. | P3: Source links are in Financial_Metrics; figures are not independently audited in this correction.
A4: MMC | B4: =Financial_Metrics!G30 -> 26.981 | C4: =Financial_Metrics!G32 -> 6.223 | D4: =Financial_Metrics!G33 -> 4.16 | E4: =IFERROR(D4/B4,"") -> 0.15418257 | F4: =Financial_Metrics!G40 -> 1.1904762 | G4: =IFERROR(Financial_Metrics!G41/B4,"") -> 0.49664579 | H4: =Financial_Metrics!G35 -> 5.3 | I4: =Financial_Metrics!G37 -> 4.6 | J4: =IFERROR(I4/B4,"") -> 0.17049035 | K4: FY2025 reported values linked from Financial_Metrics; other linked ratios remain provisional where source inputs are unverified. | L4: =Stress_Test_Matrix!E11 -> 5.445125 | M4: =Stress_Test_Matrix!E12 -> 4.66725 | N4: =Stress_Test_Matrix!F12 -> 4.8617187 | O4: Peer comparison is descriptive; verify source inputs and definitions before drawing investment conclusions. | P4: Source links are in Financial_Metrics; figures are not independently audited in this correction.
A5: AJG | B5: =Financial_Metrics!G44 -> 13.942 | C5: =Financial_Metrics!G46 -> 2.51 | D5: =Financial_Metrics!G47 -> 1.494 | E5: =IFERROR(D5/B5,"") -> 0.10715823 | F5: =Financial_Metrics!G54 -> 1.25 | G5: =IFERROR(Financial_Metrics!G55/B5,"") -> 0.56663319 | H5: =Financial_Metrics!G49 -> 2.4 | I5: =Financial_Metrics!G51 -> 2.1 | J5: =IFERROR(I5/B5,"") -> 0.15062401 | K5: EBIT is a derived proxy, not directly reported EBIT; source/period comparability limited. | L5: =Stress_Test_Matrix!E15 -> 2.19625 | M5: =Stress_Test_Matrix!E16 -> 1.8825 | N5: =Stress_Test_Matrix!F16 -> 2.9460094 | O5: Peer comparison is descriptive; verify source inputs and definitions before drawing investment conclusions. | P5: Source links are in Financial_Metrics; figures are not independently audited in this correction.
A6: BRO | B6: =Financial_Metrics!G58 -> 5.902 | C6: =Financial_Metrics!G60 -> 1.668 | D6: =Financial_Metrics!G61 -> 1.054 | E6: =IFERROR(D6/B6,"") -> 0.17858353 | F6: =Financial_Metrics!G68 -> 1.4126984 | G6: =IFERROR(Financial_Metrics!G69/B6,"") -> 0.76245341 | H6: =Financial_Metrics!G63 -> 1.4 | I6: =Financial_Metrics!G65 -> 1.29 | J6: =IFERROR(I6/B6,"") -> 0.21856998 | K6: EBIT is a derived proxy, not directly reported EBIT; source/period comparability limited. | L6: =Stress_Test_Matrix!E19 -> 1.4595 | M6: =Stress_Test_Matrix!E20 -> 1.251 | N6: =Stress_Test_Matrix!F20 -> 4.2121212 | O6: Peer comparison is descriptive; verify source inputs and definitions before drawing investment conclusions. | P6: Source links are in Financial_Metrics; figures are not independently audited in this correction.
A8: Interpretation note | B8: This peer panel is descriptive. It is not a calibrated default-probability model. FY2025 values are linked to the Financial_Metrics sheet; see Audit_Log for corrected figures and remaining verification gaps.

Sheet Review_Flags
A1: Priority | B1: Area | C1: Cells / scope | D1: Current finding | E1: Action required | F1: Status
A2: High | B2: Historical source values | C2: Financial_Metrics C:D and H; all companies | D2: 2021–2022 and 2026_TTM values are not fully reconciled. Some older values are rounded estimates while prior statuses implied confirmation. | E2: Reconcile each remaining value to issuer annual/interim filings; change status only after checking the source line. | F2: Open
A3: Resolved in part | B3: Revenue growth spikes | C3: Financial_Metrics rows 17,31,45,59 | D3: FY2023–FY2025 revenues for Aon, MMC, AJG and BRO were updated from FY2025 Form 10-Ks. Growth formulas now recalculate from the corrected reported revenue values. | E3: Review 2021–2022 revenue inputs and check organic vs reported growth separately if discussing business performance. | F3: Partially resolved
A4: Resolved | B4: WTW FY2024 net income | C4: Financial_Metrics F5 | D4: Updated from -0.100 to -0.098 USD bn, consistent with net income attributable to WTW in the FY2025 Form 10-K; the reported attributable net loss is real and linked to significant TRANZACT-related items. | E4: Retain the caveat about non-recurring impairment/disposal effects; do not compare net margin without context. | F4: Resolved for FY2024
A5: High | B5: WTW FY2021 net income | C5: Financial_Metrics C5 | D5: Value 4.22 remains unverified in this pass and is an outlier versus adjacent years. | E5: Check FY2021 Form 10-K and whether the figure is attributable net income, continuing operations, or includes discontinued operations. | F5: Open
A6: High | B6: WTW capex / interest expense overlap | C6: Financial_Metrics C8:E8 vs C14:E14 | D6: Values remain identical for 2021–2023; FY2024 and FY2025 were corrected to capex 0.245/0.229 and interest expense 0.263/0.260. | E6: Verify WTW FY2021–FY2023 cash-flow capex and interest expense separately. | F6: Partially resolved
A7: Medium | B7: Interest expense series | C7: Financial_Metrics rows 14,28,42,56,70 | D7: FY2025 values for all five companies are now tied to the 2025 10-Ks. Several older periods remain unverified; interest definitions may differ by issuer. | E7: Reconcile every remaining year. Add explanatory note for large changes due to debt issuance/acquisitions rather than treating a spike as an error. | F7: Partially resolved
A8: Resolved | B8: FY2026 TTM growth comparison | C8: Financial_Metrics H3,H17,H31,H45,H59 | D8: TTM was previously divided by FY2025 and labelled as YoY. The TTM growth cell is now explicitly unavailable because a comparable prior TTM period is not present. | E8: If desired, add TTM ending date and prior-year same-period values to calculate true TTM YoY. | F8: Resolved
A9: High | B9: Balance-sheet inputs | C9: Financial_Metrics rows for Current Assets, Current Liabilities, Total Debt | D9: These inputs and their derived ratios remain provisional because every value has not been reconciled to balance-sheet/debt-note line items. | E9: Verify current/noncurrent classification and whether debt means interest-bearing debt; then update current ratio and debt/revenue. | F9: Open
A10: High | B10: Cash-flow inputs | C10: Financial_Metrics rows for Operating Cash Flow, Capital Expenditures, Free Cash Flow | D10: Only selected WTW FY2024–FY2025 cash-flow values were updated; other company/year values remain provisional. Free cash flow is formula-driven from OCF less capex. | E10: Reconcile all cash-flow inputs and confirm the workbook’s capex sign convention. | F10: Open
A11: Medium | B11: EBIT comparability | C11: Financial_Metrics rows 46 and 60; Peer_Comparison | D11: AJG and BRO figures are labelled earnings proxies, derived as income before income taxes plus interest expense; they are not directly reported EBIT. | E11: Keep the proxy label in tables/charts, or replace with a consistently defined reported operating income if comparable line items can be sourced. | F11: Documented limitation
A12: Medium | B12: Missing ratios | C12: Financial_Ratios columns E:F | D12: Debt-to-Equity and Debt-to-EBITDA remain unavailable because total equity and comparable EBITDA inputs are not in the model. | E12: Keep as N/A until verified equity and EBITDA values are added; do not estimate missing values. | F12: Open
... A20: Medium | B20: Total debt definition | C20: Financial_Metrics Total Debt rows | D20: WTW FY2025 total debt is 6.903 with lease liabilities (current debt 550 + long-term debt 5,756 + leases 597) and 6.306 without. The other four companies' definitions are unconfirmed, which would distort Debt / Revenue and operating cash flow / debt comparisons. | E20: Pick one definition for all five companies and record it on the Methodology sheet. | F20: Open

Sheet Methodology
A1: Topic | B1: Method / Explanation | C1: Status / Limitation
A2: Data sources | B2: Official issuer FY2025 Form 10-K URLs are listed in Financial_Metrics and Audit_Log for the metrics updated in this pass. | C2: Only specified FY2023–FY2025 metrics were reconciled; this is not a full audit of every value.
A3: Units and periods | B3: Financial statement values are intended to be USD billions; ratios are multiples or percentages. | C3: Confirm units and fiscal-year definitions. 2026_TTM may not be directly comparable with fiscal years.
A4: Source-data preservation | B4: All hardcoded input values on Financial_Metrics (blue text) were preserved from the uploaded workbook. Only the "Calculated" rows were converted from static numbers to formulas; they reproduce the old values to rounding. | C4: Preservation does not mean the underlying source values have been independently verified.
A5: Formula-driven ratios | B5: Growth, margin, FCF, current ratio and interest coverage on Financial_Metrics are now live formulas; downstream ratios link to them. Current Ratio = Current Assets / Current Liabilities; Interest Coverage = EBIT / Interest Expense; FCF Margin = FCF / Revenue; OCF / Debt = Operating Cash Flow / Total Debt. | C5: Formulas are linked to Financial_Metrics; formula correctness does not validate the source inputs.
A6: Unavailable ratios | B6: Debt-to-Equity and Debt-to-EBITDA are marked unavailable. | C6: The workbook does not contain the required total equity and EBITDA inputs for reliable calculations.
A7: Stress-test method | B7: Stressed revenue = FY2025 revenue × (1 + shock). Stressed EBIT proxy = FY2025 EBIT × (1 + DOL × shock). DOL and the two coverage thresholds are single input cells at Stress_Test_Matrix!N2:N4. | C7: DOL and coverage thresholds are illustrative assumptions, not empirically estimated forecasts or credit ratings.
A8: Peer comparison | B8: FY2025 values and derived ratios are linked to Financial_Metrics; stress outputs link to Stress_Test_Matrix. | C8: Use as an analytical prototype only until each source value is reconciled to the corresponding annual report.
A9: Correction log | B9: This version restores and preserves the source values from Insurance_Brokers_Peer_Ultimate_Model (6).xlsx; formulas were added only to downstream analytical sheets. | C9: The earlier corrected version should not be used as the source of truth because it changed source figures.
A10: Review flags | B10: See the Review_Flags sheet for data anomalies found during review. | C10: These items are flagged, not changed. Source values were left as provided.
A11: FY2023–FY2025 audit pass | B11: Revenue, operating income where reported, net income and selected interest expense values were reconciled against FY2025 Form 10-Ks for WTW, Aon, MMC, AJG and BRO. | C11: This is a partial source audit, not a complete audit of all rows or years. See Audit_Log.
A12: Status semantics | B12: Verified = value traced to a specific primary-source line; Partially verified = only named periods verified; Needs review = not yet reconciled; Calculated = formula output; Derived proxy = explicitly computed substitute. | C12: Do not use unverified current assets, current liabilities, debt, cash-flow or 2026_TTM values for firm conclusions.
... A17: v4 verification pass (WTW) | B17: Each WTW input was compared with the FY2025 Form 10-K (income statement, cash-flow statement, balance sheet). Values read from the filing are marked Verified or Corrected on Source_Verification; values seen only on aggregator sites are shown as cross-checks and never overwrite the model. Corrections keep the old value in Audit_Log. Revenue is derived as total costs of providing services plus income from operations. Total debt includes lease liabilities (see Review_Flags). Operating Profit Margin (EBIT / Revenue) was added to Financial_Ratios, column K. | C17: Aon, MMC, AJG and BRO are not yet re-verified. Page numbers are not recorded: the filing was read as text, so statements are cited by name. Date checked: 2026-10-28.

Sheet Source_Verification
A1: Source verification register
A2: Each row compares one model input with a source. Only values read from the SEC filing are marked verified; values seen on aggregator sites are listed as cross-checks and are never used to overwrite the model. Pass 1 covers WTW; Aon, MMC, AJG and BRO are not yet checked.
A4: Company | B4: Metric | C4: Period | D4: Model cell | E4: Value before audit (USD bn) | F4: Source value (USD mn) | G4: Source value (USD bn) | H4: Current model value (USD bn) | I4: Difference (model − source) | J4: Live check | K4: Verification status | L4: Source type | M4: Source document / site | N4: Statement / section | O4: Page | P4: Source URL | Q4: Date checked | R4: Notes
A5: WTW | B5: Revenue | C5: 2025 | D5: G2 | E5: 9.708 | F5: =7474+2234 -> 9708 | G5: =F5/1000 -> 9.708 | H5: =Financial_Metrics!G2 -> 9.708 | I5: =H5-G5 -> 0 | J5: =IF(ABS(I5)<=0.0005,"Match",IF(ABS(I5)<=0.01,"Rounding","Mismatch")) -> Match | K5: Verified — primary | L5: Primary — SEC filing | M5: WTW Form 10-K, FY ended 31 Dec 2025 (SEC EDGAR) | N5: Consolidated Statements of Comprehensive Income | O5: Item 8 (starts p.71); exact page not captured | P5: https://www.sec.gov/Archives/edgar/data/1140536/000119312526069307/wtw-20251231.htm | Q5: 46323 | R5: Derived: total costs of providing services 7,474 + income from operations 2,234 (revenue line itself not viewed).
A6: WTW | B6: Revenue | C6: 2024 | D6: F2 | E6: 9.93 | F6: =9303+627 -> 9930 | G6: =F6/1000 -> 9.93 | H6: =Financial_Metrics!F2 -> 9.93 | I6: =H6-G6 -> 0 | J6: =IF(ABS(I6)<=0.0005,"Match",IF(ABS(I6)<=0.01,"Rounding","Mismatch")) -> Match | K6: Verified — primary | L6: Primary — SEC filing | M6: WTW Form 10-K, FY ended 31 Dec 2025 (SEC EDGAR) | N6: Consolidated Statements of Comprehensive Income | O6: Item 8 (starts p.71); exact page not captured | P6: https://www.sec.gov/Archives/edgar/data/1140536/000119312526069307/wtw-20251231.htm | Q6: 46323 | R6: Derived: total costs 9,303 + income from operations 627.
A7: WTW | B7: Revenue | C7: 2023 | D7: E2 | E7: 9.483 | F7: =8118+1365 -> 9483 | G7: =F7/1000 -> 9.483 | H7: =Financial_Metrics!E2 -> 9.483 | I7: =H7-G7 -> 0 | J7: =IF(ABS(I7)<=0.0005,"Match",IF(ABS(I7)<=0.01,"Rounding","Mismatch")) -> Match | K7: Verified — primary | L7: Primary — SEC filing | M7: WTW Form 10-K, FY ended 31 Dec 2025 (SEC EDGAR) | N7: Consolidated Statements of Comprehensive Income | O7: Item 8 (starts p.71); exact page not captured | P7: https://www.sec.gov/Archives/edgar/data/1140536/000119312526069307/wtw-20251231.htm | Q7: 46323 | R7: Derived: total costs 8,118 + income from operations 1,365.
A8: WTW | B8: EBIT | C8: 2025 | D8: G4 | E8: 2.234 | F8: 2234 | G8: =F8/1000 -> 2.234 | H8: =Financial_Metrics!G4 -> 2.234 | I8: =H8-G8 -> 0 | J8: =IF(ABS(I8)<=0.0005,"Match",IF(ABS(I8)<=0.01,"Rounding","Mismatch")) -> Match | K8: Verified — primary | L8: Primary — SEC filing | M8: WTW Form 10-K, FY ended 31 Dec 2025 (SEC EDGAR) | N8: Consolidated Statements of Comprehensive Income | O8: Item 8 (starts p.71); exact page not captured | P8: https://www.sec.gov/Archives/edgar/data/1140536/000119312526069307/wtw-20251231.htm | Q8: 46323 | R8: Income from operations.
A9: WTW | B9: EBIT | C9: 2024 | D9: F4 | E9: 0.627 | F9: 627 | G9: =F9/1000 -> 0.627 | H9: =Financial_Metrics!F4 -> 0.627 | I9: =H9-G9 -> 0 | J9: =IF(ABS(I9)<=0.0005,"Match",IF(ABS(I9)<=0.01,"Rounding","Mismatch")) -> Match | K9: Verified — primary | L9: Primary — SEC filing | M9: WTW Form 10-K, FY ended 31 Dec 2025 (SEC EDGAR) | N9: Consolidated Statements of Comprehensive Income | O9: Item 8 (starts p.71); exact page not captured | P9: https://www.sec.gov/Archives/edgar/data/1140536/000119312526069307/wtw-20251231.htm | Q9: 46323 | R9: Income from operations.
A10: WTW | B10: EBIT | C10: 2023 | D10: E4 | E10: 1.365 | F10: 1365 | G10: =F10/1000 -> 1.365 | H10: =Financial_Metrics!E4 -> 1.365 | I10: =H10-G10 -> 0 | J10: =IF(ABS(I10)<=0.0005,"Match",IF(ABS(I10)<=0.01,"Rounding","Mismatch")) -> Match | K10: Verified — primary | L10: Primary — SEC filing | M10: WTW Form 10-K, FY ended 31 Dec 2025 (SEC EDGAR) | N10: Consolidated Statements of Comprehensive Income | O10: Item 8 (starts p.71); exact page not captured | P10: https://www.sec.gov/Archives/edgar/data/1140536/000119312526069307/wtw-20251231.htm | Q10: 46323 | R10: Income from operations.
A11: WTW | B11: Net income attributable | C11: 2025 | D11: G5 | E11: 1.605 | F11: 1605 | G11: =F11/1000 -> 1.605 | H11: =Financial_Metrics!G5 -> 1.605 | I11: =H11-G11 -> 0 | J11: =IF(ABS(I11)<=0.0005,"Match",IF(ABS(I11)<=0.01,"Rounding","Mismatch")) -> Match | K11: Verified — primary | L11: Primary — SEC filing | M11: WTW Form 10-K, FY ended 31 Dec 2025 (SEC EDGAR) | N11: Consolidated Statements of Comprehensive Income | O11: Item 8 (starts p.71); exact page not captured | P11: https://www.sec.gov/Archives/edgar/data/1140536/000119312526069307/wtw-20251231.htm | Q11: 46323 | R11: Net income attributable to WTW.
A12: WTW | B12: Net income attributable | C12: 2024 | D12: F5 | E12: -0.098 | F12: -98 | G12: =F12/1000 -> -0.098 | H12: =Financial_Metrics!F5 -> -0.098 | I12: =H12-G12 -> 0 | J12: =IF(ABS(I12)<=0.0005,"Match",IF(ABS(I12)<=0.01,"Rounding","Mismatch")) -> Match | K12: Verified — primary | L12: Primary — SEC filing | M12: WTW Form 10-K, FY ended 31 Dec 2025 (SEC EDGAR) | N12: Consolidated Statements of Comprehensive Income | O12: Item 8 (starts p.71); exact page not captured | P12: https://www.sec.gov/Archives/edgar/data/1140536/000119312526069307/wtw-20251231.htm | Q12: 46323 | R12: Net loss attributable to WTW.
A13: WTW | B13: Net income attributable | C13: 2023 | D13: E5 | E13: 1.064 | F13: 1055 | G13: =F13/1000 -> 1.055 | H13: =Financial_Metrics!E5 -> 1.055 | I13: =H13-G13 -> 0 | J13: =IF(ABS(I13)<=0.0005,"Match",IF(ABS(I13)<=0.01,"Rounding","Mismatch")) -> Match | K13: Corrected — primary | L13: Primary — SEC filing | M13: WTW Form 10-K, FY ended 31 Dec 2025 (SEC EDGAR) | N13: Consolidated Statements of Comprehensive Income | O13: Item 8 (starts p.71); exact page not captured | P13: https://www.sec.gov/Archives/edgar/data/1140536/000119312526069307/wtw-20251231.htm | Q13: 46323 | R13: Attributable to WTW. Consolidated net income was 1,064 (before 9 non-controlling interests).
A14: WTW | B14: Interest expense | C14: 2025 | D14: G14 | E14: 0.26 | F14: 260 | G14: =F14/1000 -> 0.26 | H14: =Financial_Metrics!G14 -> 0.26 | I14: =H14-G14 -> 0 | J14: =IF(ABS(I14)<=0.0005,"Match",IF(ABS(I14)<=0.01,"Rounding","Mismatch")) -> Match | K14: Verified — primary | L14: Primary — SEC filing | M14: WTW Form 10-K, FY ended 31 Dec 2025 (SEC EDGAR) | N14: Consolidated Statements of Comprehensive Income | O14: Item 8 (starts p.71); exact page not captured | P14: https://www.sec.gov/Archives/edgar/data/1140536/000119312526069307/wtw-20251231.htm | Q14: 46323 | R14: Interest expense.
A15: WTW | B15: Interest expense | C15: 2024 | D15: F14 | E15: 0.263 | F15: 263 | G15: =F15/1000 -> 0.263 | H15: =Financial_Metrics!F14 -> 0.263 | I15: =H15-G15 -> 0 | J15: =IF(ABS(I15)<=0.0005,"Match",IF(ABS(I15)<=0.01,"Rounding","Mismatch")) -> Match | K15: Verified — primary | L15: Primary — SEC filing | M15: WTW Form 10-K, FY ended 31 Dec 2025 (SEC EDGAR) | N15: Consolidated Statements of Comprehensive Income | O15: Item 8 (starts p.71); exact page not captured | P15: https://www.sec.gov/Archives/edgar/data/1140536/000119312526069307/wtw-20251231.htm | Q15: 46323 | R15: Interest expense.
A16: WTW | B16: Interest expense | C16: 2023 | D16: E14 | E16: 0.3 | F16: 235 | G16: =F16/1000 -> 0.235 | H16: =Financial_Metrics!E14 -> 0.235 | I16: =H16-G16 -> 0 | J16: =IF(ABS(I16)<=0.0005,"Match",IF(ABS(I16)<=0.01,"Rounding","Mismatch")) -> Match | K16: Corrected — primary | L16: Primary — SEC filing | M16: WTW Form 10-K, FY ended 31 Dec 2025 (SEC EDGAR) | N16: Consolidated Statements of Comprehensive Income | O16: Item 8 (starts p.71); exact page not captured | P16: https://www.sec.gov/Archives/edgar/data/1140536/000119312526069307/wtw-20251231.htm | Q16: 46323 | R16: Interest expense.
A17: WTW | B17: Operating cash flow | C17: 2025 | D17: G7 | E17: 1.775 | F17: 1775 | G17: =F17/1000 -> 1.775 | H17: =Financial_Metrics!G7 -> 1.775 | I17: =H17-G17 -> 0 | J17: =IF(ABS(I17)<=0.0005,"Match",IF(ABS(I17)<=0.01,"Rounding","Mismatch")) -> Match | K17: Verified — primary | L17: Primary — SEC filing | M17: WTW Form 10-K, FY ended 31 Dec 2025 (SEC EDGAR) | N17: Consolidated Statements of Cash Flows | O17: Item 8 (starts p.71); exact page not captured | P17: https://www.sec.gov/Archives/edgar/data/1140536/000119312526069307/wtw-20251231.htm | Q17: 46323 | R17: Net cash from operating activities.
A18: WTW | B18: Operating cash flow | C18: 2024 | D18: F7 | E18: 1.512 | F18: 1512 | G18: =F18/1000 -> 1.512 | H18: =Financial_Metrics!F7 -> 1.512 | I18: =H18-G18 -> 0 | J18: =IF(ABS(I18)<=0.0005,"Match",IF(ABS(I18)<=0.01,"Rounding","Mismatch")) -> Match | K18: Verified — primary | L18: Primary — SEC filing | M18: WTW Form 10-K, FY ended 31 Dec 2025 (SEC EDGAR) | N18: Consolidated Statements of Cash Flows | O18: Item 8 (starts p.71); exact page not captured | P18: https://www.sec.gov/Archives/edgar/data/1140536/000119312526069307/wtw-20251231.htm | Q18: 46323 | R18: Net cash from operating activities.
A19: WTW | B19: Operating cash flow | C19: 2023 | D19: E7 | E19: 1.49 | F19: 1345 | G19: =F19/1000 -> 1.345 | H19: =Financial_Metrics!E7 -> 1.345 | I19: =H19-G19 -> 0 | J19: =IF(ABS(I19)<=0.0005,"Match",IF(ABS(I19)<=0.01,"Rounding","Mismatch")) -> Match | K19: Corrected — primary | L19: Primary — SEC filing | M19: WTW Form 10-K, FY ended 31 Dec 2025 (SEC EDGAR) | N19: Consolidated Statements of Cash Flows | O19: Item 8 (starts p.71); exact page not captured | P19: https://www.sec.gov/Archives/edgar/data/1140536/000119312526069307/wtw-20251231.htm | Q19: 46323 | R19: Net cash from operating activities.
A20: WTW | B20: Capital expenditures | C20: 2025 | D20: G8 | E20: 0.229 | F20: 229 | G20: =F20/1000 -> 0.229 | H20: =Financial_Metrics!G8 -> 0.229 | I20: =H20-G20 -> 0 | J20: =IF(ABS(I20)<=0.0005,"Match",IF(ABS(I20)<=0.01,"Rounding","Mismatch")) -> Match | K20: Verified — primary | L20: Primary — SEC filing | M20: WTW Form 10-K, FY ended 31 Dec 2025 (SEC EDGAR) | N20: Consolidated Statements of Cash Flows | O20: Item 8 (starts p.71); exact page not captured | P20: https://www.sec.gov/Archives/edgar/data/1140536/000119312526069307/wtw-20251231.htm | Q20: 46323 | R20: Additions to fixed assets and software (shown as outflow).
A21: WTW | B21: Capital expenditures | C21: 2024 | D21: F8 | E21: 0.245 | F21: 245 | G21: =F21/1000 -> 0.245 | H21: =Financial_Metrics!F8 -> 0.245 | I21: =H21-G21 -> 0 | J21: =IF(ABS(I21)<=0.0005,"Match",IF(ABS(I21)<=0.01,"Rounding","Mismatch")) -> Match | K21: Verified — primary | L21: Primary — SEC filing | M21: WTW Form 10-K, FY ended 31 Dec 2025 (SEC EDGAR) | N21: Consolidated Statements of Cash Flows | O21: Item 8 (starts p.71); exact page not captured | P21: https://www.sec.gov/Archives/edgar/data/1140536/000119312526069307/wtw-20251231.htm | Q21: 46323 | R21: Additions to fixed assets and software.
A22: WTW | B22: Capital expenditures | C22: 2023 | D22: E8 | E22: 0.3 | F22: 242 | G22: =F22/1000 -> 0.242 | H22: =Financial_Metrics!E8 -> 0.242 | I22: =H22-G22 -> 0 | J22: =IF(ABS(I22)<=0.0005,"Match",IF(ABS(I22)<=0.01,"Rounding","Mismatch")) -> Match | K22: Corrected — primary | L22: Primary — SEC filing | M22: WTW Form 10-K, FY ended 31 Dec 2025 (SEC EDGAR) | N22: Consolidated Statements of Cash Flows | O22: Item 8 (starts p.71); exact page not captured | P22: https://www.sec.gov/Archives/edgar/data/1140536/000119312526069307/wtw-20251231.htm | Q22: 46323 | R22: Additions to fixed assets and software.
A23: WTW | B23: Current assets | C23: 2025 | D23: G10 | E23: 16.87 | F23: 16874 | G23: =F23/1000 -> 16.874 | H23: =Financial_Metrics!G10 -> 16.874 | I23: =H23-G23 -> 0 | J23: =IF(ABS(I23)<=0.0005,"Match",IF(ABS(I23)<=0.01,"Rounding","Mismatch")) -> Match | K23: Corrected — primary | L23: Primary — SEC filing | M23: WTW Form 10-K, FY ended 31 Dec 2025 (SEC EDGAR) | N23: Consolidated Balance Sheets | O23: Item 8 (starts p.71); exact page not captured | P23: https://www.sec.gov/Archives/edgar/data/1140536/000119312526069307/wtw-20251231.htm | Q23: 46323 | R23: Total current assets (includes fiduciary assets of 10,445).
A24: WTW | B24: Current assets | C24: 2024 | D24: F10 | E24: 16.01 | F24: 15105 | G24: =F24/1000 -> 15.105 | H24: =Financial_Metrics!F10 -> 15.105 | I24: =H24-G24 -> 0 | J24: =IF(ABS(I24)<=0.0005,"Match",IF(ABS(I24)<=0.01,"Rounding","Mismatch")) -> Match | K24: Corrected — primary | L24: Primary — SEC filing | M24: WTW Form 10-K, FY ended 31 Dec 2025 (SEC EDGAR) | N24: Consolidated Balance Sheets | O24: Item 8 (starts p.71); exact page not captured | P24: https://www.sec.gov/Archives/edgar/data/1140536/000119312526069307/wtw-20251231.htm | Q24: 46323 | R24: Total current assets (includes fiduciary assets of 9,504).
A25: WTW | B25: Current liabilities | C25: 2025 | D25: G11 | E25: 14 | F25: 14004 | G25: =F25/1000 -> 14.004 | H25: =Financial_Metrics!G11 -> 14.004 | I25: =H25-G25 -> 0 | J25: =IF(ABS(I25)<=0.0005,"Match",IF(ABS(I25)<=0.01,"Rounding","Mismatch")) -> Match | K25: Corrected — primary | L25: Primary — SEC filing | M25: WTW Form 10-K, FY ended 31 Dec 2025 (SEC EDGAR) | N25: Consolidated Balance Sheets | O25: Item 8 (starts p.71); exact page not captured | P25: https://www.sec.gov/Archives/edgar/data/1140536/000119312526069307/wtw-20251231.htm | Q25: 46323 | R25: Total current liabilities (includes fiduciary liabilities of 10,445).
A26: WTW | B26: Current liabilities | C26: 2024 | D26: F11 | E26: 13.35 | F26: 12598 | G26: =F26/1000 -> 12.598 | H26: =Financial_Metrics!F11 -> 12.598 | I26: =H26-G26 -> 0 | J26: =IF(ABS(I26)<=0.0005,"Match",IF(ABS(I26)<=0.01,"Rounding","Mismatch")) -> Match | K26: Corrected — primary | L26: Primary — SEC filing | M26: WTW Form 10-K, FY ended 31 Dec 2025 (SEC EDGAR) | N26: Consolidated Balance Sheets | O26: Item 8 (starts p.71); exact page not captured | P26: https://www.sec.gov/Archives/edgar/data/1140536/000119312526069307/wtw-20251231.htm | Q26: 46323 | R26: Total current liabilities (includes fiduciary liabilities of 9,504).
A27: WTW | B27: Total debt | C27: 2025 | D27: G13 | E27: 6.9 | F27: =550+5756+125+472 -> 6903 | G27: =F27/1000 -> 6.903 | H27: =Financial_Metrics!G13 -> 6.903 | I27: =H27-G27 -> 0 | J27: =IF(ABS(I27)<=0.0005,"Match",IF(ABS(I27)<=0.01,"Rounding","Mismatch")) -> Match | K27: Corrected — primary | L27: Primary — SEC filing | M27: WTW Form 10-K, FY ended 31 Dec 2025 (SEC EDGAR) | N27: Consolidated Balance Sheets | O27: Item 8 (starts p.71); exact page not captured | P27: https://www.sec.gov/Archives/edgar/data/1140536/000119312526069307/wtw-20251231.htm | Q27: 46323 | R27: Derived: current debt 550 + long-term debt 5,756 + current lease 125 + long-term lease 472. Excluding leases: 6,306.
A28: WTW | B28: Total debt | C28: 2024 | D28: F13 | E28: 5.94 | F28: =0+5309+118+502 -> 5929 | G28: =F28/1000 -> 5.929 | H28: =Financial_Metrics!F13 -> 5.929 | I28: =H28-G28 -> 0 | J28: =IF(ABS(I28)<=0.0005,"Match",IF(ABS(I28)<=0.01,"Rounding","Mismatch")) -> Match | K28: Corrected — primary | L28: Primary — SEC filing | M28: WTW Form 10-K, FY ended 31 Dec 2025 (SEC EDGAR) | N28: Consolidated Balance Sheets | O28: Item 8 (starts p.71); exact page not captured | P28: https://www.sec.gov/Archives/edgar/data/1140536/000119312526069307/wtw-20251231.htm | Q28: 46323 | R28: Derived: current debt 0 + long-term debt 5,309 + current lease 118 + long-term lease 502. Excluding leases: 5,309.
A29: WTW | B29: Revenue | C29: 2022 | D29: D2 | E29: 8.87 | F29: 8866 | G29: =F29/1000 -> 8.866 | H29: =Financial_Metrics!D2 -> 8.87 | I29: =H29-G29 -> 0.004 | J29: =IF(ABS(I29)<=0.0005,"Match",IF(ABS(I29)<=0.01,"Rounding","Mismatch")) -> Rounding | K29: Cross-check — rounding only (secondary) | L29: Secondary — aggregator (not primary) | M29: finboard.net; tipranks.com | N29: Aggregator table of SEC-filed data; not checked against the filing | O29: n/a | P29: https://finboard.net/companies/WTW/raw/income-statement | Q29: 46323 | R29: Rounded in model.
A30: WTW | B30: Revenue | C30: 2021 | D30: C2 | E30: 9 | F30: 8998 | G30: =F30/1000 -> 8.998 | H30: =Financial_Metrics!C2 -> 9 | I30: =H30-G30 -> 0.002 | J30: =IF(ABS(I30)<=0.0005,"Match",IF(ABS(I30)<=0.01,"Rounding","Mismatch")) -> Rounding | K30: Cross-check — rounding only (secondary) | L30: Secondary — aggregator (not primary) | M30: finboard.net; tipranks.com | N30: Aggregator table of SEC-filed data; not checked against the filing | O30: n/a | P30: https://finboard.net/companies/WTW/raw/income-statement | Q30: 46323 | R30: Rounded in model.
A31: WTW | B31: EBIT | C31: 2022 | D31: D4 | E31: 1.81 | F31: 1178 | G31: =F31/1000 -> 1.178 | H31: =Financial_Metrics!D4 -> 1.81 | I31: =H31-G31 -> 0.632 | J31: =IF(ABS(I31)<=0.0005,"Match",IF(ABS(I31)<=0.01,"Rounding","Mismatch")) -> Mismatch | K31: Discrepancy — secondary only, model not changed | L31: Secondary — aggregator (not primary) | M31: finboard.net (single source) | N31: Aggregator table of SEC-filed data; not checked against the filing | O31: n/a | P31: https://finboard.net/companies/WTW/raw/income-statement | Q31: 46323
A32: WTW | B32: EBIT | C32: 2021 | D32: C4 | E32: 1.75 | F32: 2202 | G32: =F32/1000 -> 2.202 | H32: =Financial_Metrics!C4 -> 1.75 | I32: =H32-G32 -> -0.452 | J32: =IF(ABS(I32)<=0.0005,"Match",IF(ABS(I32)<=0.01,"Rounding","Mismatch")) -> Mismatch | K32: Discrepancy — secondary only, model not changed | L32: Secondary — aggregator (not primary) | M32: finboard.net (single source) | N32: Aggregator table of SEC-filed data; not checked against the filing | O32: n/a | P32: https://finboard.net/companies/WTW/raw/income-statement | Q32: 46323
A33: WTW | B33: Net income attributable | C33: 2022 | D33: D5 | E33: 1.01 | F33: 1009 | G33: =F33/1000 -> 1.009 | H33: =Financial_Metrics!D5 -> 1.01 | I33: =H33-G33 -> 0.001 | J33: =IF(ABS(I33)<=0.0005,"Match",IF(ABS(I33)<=0.01,"Rounding","Mismatch")) -> Rounding | K33: Cross-check — rounding only (secondary) | L33: Secondary — aggregator (not primary) | M33: marketbeat.com; tipranks.com | N33: Aggregator table of SEC-filed data; not checked against the filing | O33: n/a | P33: https://www.marketbeat.com/stocks/NASDAQ/WTW/financials | Q33: 46323
A34: WTW | B34: Net income attributable | C34: 2021 | D34: C5 | E34: 4.22 | F34: 4222 | G34: =F34/1000 -> 4.222 | H34: =Financial_Metrics!C5 -> 4.22 | I34: =H34-G34 -> -0.002 | J34: =IF(ABS(I34)<=0.0005,"Match",IF(ABS(I34)<=0.01,"Rounding","Mismatch")) -> Rounding | K34: Cross-check — rounding only (secondary) | L34: Secondary — aggregator (not primary) | M34: marketbeat.com; tipranks.com | N34: Aggregator table of SEC-filed data; not checked against the filing | O34: n/a | P34: https://www.marketbeat.com/stocks/NASDAQ/WTW/financials | Q34: 46323 | R34: Matches the model's outlier flag: real, not an error.
A35: WTW | B35: Interest expense | C35: 2022 | D35: D14 | E35: 0.3 | F35: 208 | G35: =F35/1000 -> 0.208 | H35: =Financial_Metrics!D14 -> 0.3 | I35: =H35-G35 -> 0.092 | J35: =IF(ABS(I35)<=0.0005,"Match",IF(ABS(I35)<=0.01,"Rounding","Mismatch")) -> Mismatch | K35: Discrepancy — secondary only, model not changed | L35: Secondary — aggregator (not primary) | M35: finboard.net; chartrow.com | N35: Aggregator table of SEC-filed data; not checked against the filing | O35: n/a | P35: https://chartrow.com/quote/wtw/financials | Q35: 46323
A36: WTW | B36: Interest expense | C36: 2021 | D36: C14 | E36: 0.28 | F36: 211 | G36: =F36/1000 -> 0.211 | H36: =Financial_Metrics!C14 -> 0.28 | I36: =H36-G36 -> 0.069 | J36: =IF(ABS(I36)<=0.0005,"Match",IF(ABS(I36)<=0.01,"Rounding","Mismatch")) -> Mismatch | K36: Discrepancy — secondary only, model not changed | L36: Secondary — aggregator (not primary) | M36: finboard.net; chartrow.com | N36: Aggregator table of SEC-filed data; not checked against the filing | O36: n/a | P36: https://chartrow.com/quote/wtw/financials | Q36: 46323
A37: WTW | B37: Operating cash flow | C37: 2022 | D37: D7 | E37: 0.97 | F37: 812 | G37: =F37/1000 -> 0.812 | H37: =Financial_Metrics!D7 -> 0.97 | I37: =H37-G37 -> 0.158 | J37: =IF(ABS(I37)<=0.0005,"Match",IF(ABS(I37)<=0.01,"Rounding","Mismatch")) -> Mismatch | K37: Discrepancy — secondary only, model not changed | L37: Secondary — aggregator (not primary) | M37: stockopedia.com; stockanalysis.com | N37: Aggregator table of SEC-filed data; not checked against the filing | O37: n/a | P37: https://stockanalysis.com/stocks/wtw/financials/cash-flow-statement/ | Q37: 46323
A38: WTW | B38: Operating cash flow | C38: 2021 | D38: C7 | E38: 2.11 | F38: 2061 | G38: =F38/1000 -> 2.061 | H38: =Financial_Metrics!C7 -> 2.11 | I38: =H38-G38 -> 0.049 | J38: =IF(ABS(I38)<=0.0005,"Match",IF(ABS(I38)<=0.01,"Rounding","Mismatch")) -> Mismatch | K38: Discrepancy — secondary only, model not changed | L38: Secondary — aggregator (not primary) | M38: stockopedia.com; stockanalysis.com | N38: Aggregator table of SEC-filed data; not checked against the filing | O38: n/a | P38: https://stockanalysis.com/stocks/wtw/financials/cash-flow-statement/ | Q38: 46323
A39: WTW | B39: Capital expenditures | C39: 2022 | D39: D8 | E39: 0.3 | F39: 204 | G39: =F39/1000 -> 0.204 | H39: =Financial_Metrics!D8 -> 0.3 | I39: =H39-G39 -> 0.096 | J39: =IF(ABS(I39)<=0.0005,"Match",IF(ABS(I39)<=0.01,"Rounding","Mismatch")) -> Mismatch | K39: Discrepancy — secondary only, model not changed | L39: Secondary — aggregator (not primary) | M39: stockopedia.com; stockanalysis.com | N39: Aggregator table of SEC-filed data; not checked against the filing | O39: n/a | P39: https://stockanalysis.com/stocks/wtw/financials/cash-flow-statement/ | Q39: 46323 | R39: Fixed assets 138 + intangibles 66.
A40: WTW | B40: Capital expenditures | C40: 2021 | D40: C8 | E40: 0.28 | F40: 201 | G40: =F40/1000 -> 0.201 | H40: =Financial_Metrics!C8 -> 0.28 | I40: =H40-G40 -> 0.079 | J40: =IF(ABS(I40)<=0.0005,"Match",IF(ABS(I40)<=0.01,"Rounding","Mismatch")) -> Mismatch | K40: Discrepancy — secondary only, model not changed | L40: Secondary — aggregator (not primary) | M40: stockopedia.com; stockanalysis.com | N40: Aggregator table of SEC-filed data; not checked against the filing | O40: n/a | P40: https://stockanalysis.com/stocks/wtw/financials/cash-flow-statement/ | Q40: 46323 | R40: Fixed assets 148 + intangibles 53.
A41: WTW | B41: Current assets | C41: 2023 | D41: E10 | E41: 14.06 | F41: 13433 | G41: =F41/1000 -> 13.433 | H41: =Financial_Metrics!E10 -> 14.06 | I41: =H41-G41 -> 0.627 | J41: =IF(ABS(I41)<=0.0005,"Match",IF(ABS(I41)<=0.01,"Rounding","Mismatch")) -> Mismatch | K41: Discrepancy — secondary only, model not changed | L41: Secondary — aggregator (not primary) | M41: app.edgar.tools; stockanalysis.com; finboard.net | N41: Aggregator table of SEC-filed data; not checked against the filing | O41: n/a | P41: https://app.edgar.tools/companies/WTW | Q41: 46323 | R41: FY2023 10-K not retrieved.
A42: WTW | B42: Current assets | C42: 2022 | D42: D10 | E42: 13.83 | F42: 15835 | G42: =F42/1000 -> 15.835 | H42: =Financial_Metrics!D10 -> 13.83 | I42: =H42-G42 -> -2.005 | J42: =IF(ABS(I42)<=0.0005,"Match",IF(ABS(I42)<=0.01,"Rounding","Mismatch")) -> Mismatch | K42: Discrepancy — secondary only, model not changed | L42: Secondary — aggregator (not primary) | M42: app.edgar.tools; stockanalysis.com; finboard.net | N42: Aggregator table of SEC-filed data; not checked against the filing | O42: n/a | P42: https://app.edgar.tools/companies/WTW | Q42: 46323
A43: WTW | B43: Current assets | C43: 2021 | D43: C10 | E43: 13.5 | F43: 18488 | G43: =F43/1000 -> 18.488 | H43: =Financial_Metrics!C10 -> 13.5 | I43: =H43-G43 -> -4.988 | J43: =IF(ABS(I43)<=0.0005,"Match",IF(ABS(I43)<=0.01,"Rounding","Mismatch")) -> Mismatch | K43: Discrepancy — secondary only, model not changed | L43: Secondary — aggregator (not primary) | M43: app.edgar.tools; stockanalysis.com; finboard.net | N43: Aggregator table of SEC-filed data; not checked against the filing | O43: n/a | P43: https://app.edgar.tools/companies/WTW | Q43: 46323
A44: WTW | B44: Current liabilities | C44: 2023 | D44: E11 | E44: 13.26 | F44: 12630 | G44: =F44/1000 -> 12.63 | H44: =Financial_Metrics!E11 -> 13.26 | I44: =H44-G44 -> 0.63 | J44: =IF(ABS(I44)<=0.0005,"Match",IF(ABS(I44)<=0.01,"Rounding","Mismatch")) -> Mismatch | K44: Discrepancy — secondary only, model not changed | L44: Secondary — aggregator (not primary) | M44: app.edgar.tools; stockanalysis.com; finboard.net | N44: Aggregator table of SEC-filed data; not checked against the filing | O44: n/a | P44: https://app.edgar.tools/companies/WTW | Q44: 46323 | R44: FY2023 10-K not retrieved.
A45: WTW | B45: Current liabilities | C45: 2022 | D45: D11 | E45: 12.93 | F45: 14779 | G45: =F45/1000 -> 14.779 | H45: =Financial_Metrics!D11 -> 12.93 | I45: =H45-G45 -> -1.849 | J45: =IF(ABS(I45)<=0.0005,"Match",IF(ABS(I45)<=0.01,"Rounding","Mismatch")) -> Mismatch | K45: Discrepancy — secondary only, model not changed | L45: Secondary — aggregator (not primary) | M45: app.edgar.tools; stockanalysis.com; finboard.net | N45: Aggregator table of SEC-filed data; not checked against the filing | O45: n/a | P45: https://app.edgar.tools/companies/WTW | Q45: 46323
A46: WTW | B46: Current liabilities | C46: 2021 | D46: C11 | E46: 12.6 | F46: 14724 | G46: =F46/1000 -> 14.724 | H46: =Financial_Metrics!C11 -> 12.6 | I46: =H46-G46 -> -2.124 | J46: =IF(ABS(I46)<=0.0005,"Match",IF(ABS(I46)<=0.01,"Rounding","Mismatch")) -> Mismatch | K46: Discrepancy — secondary only, model not changed | L46: Secondary — aggregator (not primary) | M46: app.edgar.tools; stockanalysis.com; finboard.net | N46: Aggregator table of SEC-filed data; not checked against the filing | O46: n/a | P46: https://app.edgar.tools/companies/WTW | Q46: 46323
A47: WTW | B47: Total debt | C47: 2023 | D47: E13 | E47: 5.95 | F47: 5934 | G47: =F47/1000 -> 5.934 | H47: =Financial_Metrics!E13 -> 5.95 | I47: =H47-G47 -> 0.016 | J47: =IF(ABS(I47)<=0.0005,"Match",IF(ABS(I47)<=0.01,"Rounding","Mismatch")) -> Mismatch | K47: Discrepancy — secondary only, model not changed | L47: Secondary — aggregator (not primary) | M47: stockanalysis.com (incl. leases) | N47: Aggregator table of SEC-filed data; not checked against the filing | O47: n/a | P47: https://stockanalysis.com/stocks/wtw/financials/balance-sheet/ | Q47: 46323 | R47: Incl. leases; excl. leases 5,217.
A48: WTW | B48: Total debt | C48: 2022 | D48: D13 | E48: 5.48 | F48: 5467 | G48: =F48/1000 -> 5.467 | H48: =Financial_Metrics!D13 -> 5.48 | I48: =H48-G48 -> 0.013 | J48: =IF(ABS(I48)<=0.0005,"Match",IF(ABS(I48)<=0.01,"Rounding","Mismatch")) -> Mismatch | K48: Discrepancy — secondary only, model not changed | L48: Secondary — aggregator (not primary) | M48: stockanalysis.com (incl. leases) | N48: Aggregator table of SEC-filed data; not checked against the filing | O48: n/a | P48: https://stockanalysis.com/stocks/wtw/financials/balance-sheet/ | Q48: 46323 | R48: Incl. leases.
A49: WTW | B49: Total debt | C49: 2021 | D49: C13 | E49: 5.49 | F49: 5471 | G49: =F49/1000 -> 5.471 | H49: =Financial_Metrics!C13 -> 5.49 | I49: =H49-G49 -> 0.019 | J49: =IF(ABS(I49)<=0.0005,"Match",IF(ABS(I49)<=0.01,"Rounding","Mismatch")) -> Mismatch | K49: Discrepancy — secondary only, model not changed | L49: Secondary — aggregator (not primary) | M49: stockanalysis.com (incl. leases) | N49: Aggregator table of SEC-filed data; not checked against the filing | O49: n/a | P49: https://stockanalysis.com/stocks/wtw/financials/balance-sheet/ | Q49: 46323 | R49: Incl. leases.
A50: WTW | B50: Operating cash flow | C50: 2026_TTM | D50: H7 | E50: 2.04 | F50: 1800 | G50: =F50/1000 -> 1.8 | H50: =Financial_Metrics!H7 -> 2.04 | I50: =H50-G50 -> 0.24 | J50: =IF(ABS(I50)<=0.0005,"Match",IF(ABS(I50)<=0.01,"Rounding","Mismatch")) -> Mismatch | K50: Discrepancy — secondary only, model not changed | L50: Secondary — aggregator (not primary) | M50: stockopedia.com; stockanalysis.com | N50: Aggregator table of SEC-filed data; not checked against the filing | O50: n/a | P50: https://stockanalysis.com/stocks/wtw/financials/cash-flow-statement/ | Q50: 46323 | R50: TTM to Mar-2026 (Q1 10-Q). Model's TTM period end is undefined; a later 10-Q is now available.
A51: WTW | B51: Capital expenditures | C51: 2026_TTM | D51: H8 | E51: 0.35 | F51: 233 | G51: =F51/1000 -> 0.233 | H51: =Financial_Metrics!H8 -> 0.35 | I51: =H51-G51 -> 0.117 | J51: =IF(ABS(I51)<=0.0005,"Match",IF(ABS(I51)<=0.01,"Rounding","Mismatch")) -> Mismatch | K51: Discrepancy — secondary only, model not changed | L51: Secondary — aggregator (not primary) | M51: stockopedia.com; stockanalysis.com | N51: Aggregator table of SEC-filed data; not checked against the filing | O51: n/a | P51: https://stockanalysis.com/stocks/wtw/financials/cash-flow-statement/ | Q51: 46323 | R51: TTM to Mar-2026. See note above.

Sheet Audit_Log
A1: Company | B1: Metric | C1: Period | D1: Previous value | E1: Updated value | F1: Primary source | G1: Audit status / method
A2: WTW | B2: Total Revenue | C2: 2023 | D2: 9.48 | E2: 9.483 | F2: https://www.sec.gov/Archives/edgar/data/1140536/000119312526069307/wtw-20251231.htm | G2: Updated from FY2025 Form 10-K; USD bn
A3: WTW | B3: Operating Income (EBIT) | C3: 2023 | D3: 1.93 | E3: 1.365 | F3: https://www.sec.gov/Archives/edgar/data/1140536/000119312526069307/wtw-20251231.htm | G3: Updated from FY2025 Form 10-K; USD bn
A4: WTW | B4: Operating Income (EBIT) | C4: 2024 | D4: 2.2 | E4: 0.627 | F4: https://www.sec.gov/Archives/edgar/data/1140536/000119312526069307/wtw-20251231.htm | G4: Updated from FY2025 Form 10-K; USD bn
A5: WTW | B5: Net Income | C5: 2023 | D5: 1.06 | E5: 1.064 | F5: https://www.sec.gov/Archives/edgar/data/1140536/000119312526069307/wtw-20251231.htm | G5: Updated from FY2025 Form 10-K; USD bn
A6: WTW | B6: Net Income | C6: 2024 | D6: -0.1 | E6: -0.098 | F6: https://www.sec.gov/Archives/edgar/data/1140536/000119312526069307/wtw-20251231.htm | G6: Updated to net loss attributable to WTW per FY2025 Form 10-K; USD bn
A7: WTW | B7: Operating Cash Flow | C7: 2024 | D7: 1.61 | E7: 1.512 | F7: https://www.sec.gov/Archives/edgar/data/1140536/000119312526069307/wtw-20251231.htm | G7: Updated from FY2025 Form 10-K; USD bn
A8: WTW | B8: Operating Cash Flow | C8: 2025 | D8: 1.89 | E8: 1.775 | F8: https://www.sec.gov/Archives/edgar/data/1140536/000119312526069307/wtw-20251231.htm | G8: Updated from FY2025 Form 10-K; USD bn
A9: WTW | B9: Capital Expenditures | C9: 2024 | D9: 0.34 | E9: 0.245 | F9: https://www.sec.gov/Archives/edgar/data/1140536/000119312526069307/wtw-20251231.htm | G9: Updated from FY2025 Form 10-K; USD bn
A10: WTW | B10: Capital Expenditures | C10: 2025 | D10: 0.34 | E10: 0.229 | F10: https://www.sec.gov/Archives/edgar/data/1140536/000119312526069307/wtw-20251231.htm | G10: Updated from FY2025 Form 10-K; USD bn
A11: WTW | B11: Interest Expense | C11: 2024 | D11: 0.34 | E11: 0.263 | F11: https://www.sec.gov/Archives/edgar/data/1140536/000119312526069307/wtw-20251231.htm | G11: Updated from FY2025 Form 10-K; USD bn
A12: Aon | B12: Total Revenue | C12: 2023 | D12: 13.4 | E12: 13.376 | F12: https://www.sec.gov/Archives/edgar/data/315293/000162828026008116/aon-20251231.htm | G12: Updated from FY2025 Form 10-K; USD bn
A13: Aon | B13: Total Revenue | C13: 2024 | D13: 14.1 | E13: 15.698 | F13: https://www.sec.gov/Archives/edgar/data/315293/000162828026008116/aon-20251231.htm | G13: Updated from FY2025 Form 10-K; USD bn
... A44: BRO | B44: Interest Expense | C44: 2024 | D44: 0.13 | E44: 0.193 | F44: https://www.sec.gov/Archives/edgar/data/79282/000119312526046984/bro-20251231.htm | G44: Updated from FY2025 Form 10-K; USD bn
A45: ALL | B45: 2021–2022 financial inputs | C45: FY2021–FY2022 | D45: — | E45: — | F45: Issuer annual reports / SEC filings | G45: Needs review: not independently reconciled in this pass; original values preserved unless noted.
A46: ALL | B46: 2026_TTM | C46: TTM | D46: — | E46: — | F46: Issuer filings / interim reports | G46: Needs review: exact end date and rolling 12-month construction were not documented; not used as a year-over-year comparator.
A47: ALL | B47: Current assets / current liabilities / total debt | C47: FY2021–TTM | D47: — | E47: — | F47: Issuer balance sheets / debt notes | G47: Needs review: current workbook values are not yet reconciled to line items and definitions. Derived ratios remain provisional.
A48: ALL | B48: Operating cash flow / capital expenditures | C48: FY2021–TTM | D48: — | E48: — | F48: Issuer cash-flow statements | G48: Partially verified only where explicitly updated in Financial_Metrics. Remaining periods need source reconciliation.
A49: AJG | B49: Operating Income / EBIT Proxy | C49: FY2023–FY2025 | D49: — | E49: 1.482 / 2.256 / 2.510 | F49: https://www.sec.gov/Archives/edgar/data/354190/000162828026008662/ajg-20251231.htm | G49: Derived as income before income taxes plus interest expense; not reported EBIT. Labelled proxy to avoid false comparability.
A50: BRO | B50: Operating Income / EBIT Proxy | C50: FY2023–FY2025 | D50: — | E50: 1.336 / 1.496 / 1.668 | F50: https://www.sec.gov/Archives/edgar/data/79282/000119312526046984/bro-20251231.htm | G50: Derived as income before income taxes plus interest expense; not reported EBIT. Labelled proxy to avoid false comparability.
A51: ALL | B51: Debt-to-Equity / Debt-to-EBITDA | C51: All periods | D51: N/A | E51: N/A | F51: — | G51: Not calculated because equity and EBITDA inputs are not yet present and reconciled.
A52: WTW | B52: Net Income | C52: 2023 | D52: 1.064 | E52: 1.055 | F52: https://www.sec.gov/Archives/edgar/data/1140536/000119312526069307/wtw-20251231.htm | G52: Corrected to WTW FY2025 Form 10-K, Consolidated Statements of Comprehensive Income; USD bn; checked 2026-10-28. See Source_Verification.
A53: WTW | B53: Interest Expense | C53: 2023 | D53: 0.3 | E53: 0.235 | F53: https://www.sec.gov/Archives/edgar/data/1140536/000119312526069307/wtw-20251231.htm | G53: Corrected to WTW FY2025 Form 10-K, Consolidated Statements of Comprehensive Income; USD bn; checked 2026-10-28. See Source_Verification.
A54: WTW | B54: Operating Cash Flow | C54: 2023 | D54: 1.49 | E54: 1.345 | F54: https://www.sec.gov/Archives/edgar/data/1140536/000119312526069307/wtw-20251231.htm | G54: Corrected to WTW FY2025 Form 10-K, Consolidated Statements of Cash Flows; USD bn; checked 2026-10-28. See Source_Verification.
A55: WTW | B55: Capital Expenditures | C55: 2023 | D55: 0.3 | E55: 0.242 | F55: https://www.sec.gov/Archives/edgar/data/1140536/000119312526069307/wtw-20251231.htm | G55: Corrected to WTW FY2025 Form 10-K, Consolidated Statements of Cash Flows; USD bn; checked 2026-10-28. See Source_Verification.
A56: WTW | B56: Current Assets | C56: 2025 | D56: 16.87 | E56: 16.874 | F56: https://www.sec.gov/Archives/edgar/data/1140536/000119312526069307/wtw-20251231.htm | G56: Corrected to WTW FY2025 Form 10-K, Consolidated Balance Sheets; USD bn; checked 2026-10-28. See Source_Verification.
A57: WTW | B57: Current Assets | C57: 2024 | D57: 16.01 | E57: 15.105 | F57: https://www.sec.gov/Archives/edgar/data/1140536/000119312526069307/wtw-20251231.htm | G57: Corrected to WTW FY2025 Form 10-K, Consolidated Balance Sheets; USD bn; checked 2026-10-28. See Source_Verification.
A58: WTW | B58: Current Liabilities | C58: 2025 | D58: 14 | E58: 14.004 | F58: https://www.sec.gov/Archives/edgar/data/1140536/000119312526069307/wtw-20251231.htm | G58: Corrected to WTW FY2025 Form 10-K, Consolidated Balance Sheets; USD bn; checked 2026-10-28. See Source_Verification.
A59: WTW | B59: Current Liabilities | C59: 2024 | D59: 13.35 | E59: 12.598 | F59: https://www.sec.gov/Archives/edgar/data/1140536/000119312526069307/wtw-20251231.htm | G59: Corrected to WTW FY2025 Form 10-K, Consolidated Balance Sheets; USD bn; checked 2026-10-28. See Source_Verification.
A60: WTW | B60: Total Debt | C60: 2025 | D60: 6.9 | E60: 6.903 | F60: https://www.sec.gov/Archives/edgar/data/1140536/000119312526069307/wtw-20251231.htm | G60: Corrected to WTW FY2025 Form 10-K, Consolidated Balance Sheets; USD bn; checked 2026-10-28. See Source_Verification.
A61: WTW | B61: Total Debt | C61: 2024 | D61: 5.94 | E61: 5.929 | F61: https://www.sec.gov/Archives/edgar/data/1140536/000119312526069307/wtw-20251231.htm | G61: Corrected to WTW FY2025 Form 10-K, Consolidated Balance Sheets; USD bn; checked 2026-10-28. See Source_Verification.
